Workbook

Sheet Summary (short)
A1: Foundation | B1: Engineering | C1: Product and Process | D1: Advisory and Business Consulting | E1: Leadership and Strategy
A2: Digital & AI Terminology, AI Concepts, Tool overviews | B2: AI Systems and Architecture | C2: AI-Augmented Requirement Engineering | D2: AI & Automation Use Case Spotting | E2: Managing AI Transformations
A3: Data Literacy | B3: Agentic Software Development | C3: AI-Enhanced User Research | D3: AI Cost & Value Economics | E3: AI Workforce Strategy
A4: Personal AI Productivity | B4: AI-Driven Testing & QA | D4: Consultative Prompting | E4: Decision Making with AI
A5: Corporate Ethics & Compliance | B5: AI-Supported Code Modernization | D5: AI Ecosystem Knowledge
B6: AI-Assisted Documentation
B7: Sustainable Software & Green Coding
B15: Parellele Entwicklung | C15: Schulungsempfehlungen | D15: Wer hält den Betrieb?
A16: ASE Empfehlung: | B16: basierend auf dem Score kannst du einen Lernpfad durchlaufen, der | C16: ASE -> Literacy -> anonymes Self Assessment aus der HTML von unserer ASE externen Seite (kein Betriebsrat)

Sheet Summary (long)
A1: Roles (Brainstorming Vanessa), Target Groups
B4: Group 1 | C4: Group 2 | D4: Roles
B5: All Employees | C5: Consultants | D5: Business & Strategy Consulting | F5: Idee MLM: Als Portfolio (?)
D8: Products & Value Streams
D9: Technology Consulting
E10: Technical Engineering
E11: SW-Engineering & Architecture
D12: Application Management
E13: Service Technology
E14: Service Mgmt
D15: Project Management & Agility
E16: Project Mgmt
E17: Agility
C18: Corporate Function
D19: Support
D20: Finance
D21: HR
D22: Legal
C23: Leadership
D24: LHIND Business Manager
D25: LHIND Top Management
B28: Foundation: General Literacy | C28: Engineering Literacy | D28: Product and Process Literacy | E28: Advisory and Biz Literacy | F28: Leadership and Strategy
B29: Digital & AI Terminology, AI Concepts, Tool overviews | C29: AI Systems and Architecture | D29: AI-Augmented Requirements | E29: AI & Automation Use Case Spotting | F29: Managing AI Transformations
B30: Data Literacy & Interpretation, Critical Evaluation | C30: Agentic Software Development | D30: AI-Enhanced User Research | E30: AI Cost & Value Economics | F30: AI Workforce Strategy
B31: Digital Ethics & Compliance | C31: AI-Driven Testing & QA | E31: Consultative Prompting | F31: Decision Making with AI
B32: Personal AI Productivity | C32: AI-Supported Code Modernization | E32: AI Ecosystem Knowledge
C33: AI-Assisted Documentation

Sheet Capability
A1: AI-Literacy | B1: ID | C1: Cluster | D1: Title | E1: Full Title | F1: Description | G1: Basic | H1: Advanced | I1: Expert | J1: What is it? Why is it relevant? | K1: Business & Strategy Consulting | L1: Products & Value Streams | M1: Technology Consulting | N1: Application Management | O1: Project Management & Agility | P1: Corporate Functions | Q1: Leadership | S1: All Roles | T1: Business & Strategy Consulting | U1: Products & Value Streams | V1: Technology Consulting | W1: Application Management | X1: Project Management & Agility | Y1: Corporate Functions | Z1: Leadership
A2: 1 | B2: 1 | C2: Foundation | D2: Digital & AI Terminology, AI Concepts, Tool overviews | E2: =_xlfn.CONCAT(C2, " - ", D2) -> Foundation - Digital & AI Terminology, AI Concepts, Tool overviews | F2: This competency establishes a shared understanding of core AI and digital concepts across the organization. It includes familiarity with key terminology, distinctions between major AI approaches (e.g., Machine Learning, Deep Learning, Generative AI), basic data foundations, and awareness of commonly used AI tools and platforms. The goal is to enable everyone at LHIND to communicate clearly and credibly with clients, colleagues, and technical teams, avoiding hype-driven discussions and unrealistic expectations. A consistent conceptual grounding helps teams identify appropriate use cases, explain AI capabilities and limitations accurately, and translate technical topics into business-relevant conversations. | G2: The employee possesses a foundational literacy, ensuring they can navigate corporate communications and internal announcements without ambiguity. Taxonomic Accuracy: Correctly distinguishes and defines core concepts, understanding the hierarchical relationship (e.g., Deep Learning, Machine Learning). Vocabulary: Utilizes the corporate glossary to define standard terms (e.g., Supervised vs. Unsupervised Learning, Tokens, Hallucinations) and identifies the basic functions of approved internal AI tools. Data Awareness: Recognizes the importance of data quality in internal systems and understands the "Garbage In, Garbage Out" principle regarding company data. Tool Overview: Knows the basic, available AI tools at LHIND and understands their purpose and usages Outcome: Can actively participate in departmental meetings where AI initiatives are discussed; understands the company’s tech strategy without confusion. | H2: The employee understands the semi-formal logic of the concepts and can map business problems within their specific function (e.g., HR, Finance, Ops) to technological categories. Conceptual Mapping: Identifies which class of algorithm/method is appropriate for specific operational pain points (e.g., using Regression for forecasting sales vs. LLMs for drafting internal docs). Tool Selection: Has an overview of the common tools, tool landscape and knows the major players. Evaluates and selects appropriate tools for their team's workflows, understanding the trade-offs between speed, cost, and accuracy. Data Dependency: Understands specific data requirements (volume, privacy, compliance) for models relevant to their department and anticipates potential bias in automated decisions. Outcome: Can lead credible discussions with IT/Tech departments or vendors; writes accurate requirements for digital projects; avoids requesting infeasible AI magic for routine problems. | I2: The employee acts as a bridge between business strategy and technology, capable of guiding organizational investment and governance. Critical Evaluation: Analyzes the theoretical limitations of AI architectures to prevent the deployment of fragile systems in critical business processes (e.g., understanding why GenAI is risky for precise financial calculations). Strategic Guidance: Understands and interprets market trends, vendor claims, and emerging tech realistically Strategic Architecture: Designs or oversees comprehensive workflows, assessing the long-term ROI, maintenance costs, and scalability of AI integration within their business unit. Standardization & Governance: Actively refines the internal glossary, mentors team members to correct misconceptions, and ensures the department remains resilient against external vendor hype. Outcome: Acts as a trusted advisor to Senior Leadership on digital transformation; validates the business case and technical soundness of major internal investments. | J2: What: Konzepte (ML, DL, GenAI), Glossar, Datengrundlage, Tool basics Why: Gemeinsame Sprache in der Org, Credible client conversations, avoids hype/misuse | K2: Advanced | L2: Advanced | M2: Expert | N2: Advanced | O2: Advanced | P2: Advanced | Q2: Advanced | S2: Basic What Is Copilot? An Overview of Microsoft’s AI Tools: https://www.linkedin.com/learning/what-is-copilot-an-overview-of-microsoft-s-ai-tools/use-copilot-on-the-web-in-windows-or-the-mobile-app Everyday AI Business Tools: https://www.linkedin.com/learning/everyday-ai-business-tools/exploring-essential-ai-tools-for-eveyday-business Agentic AI: A Framework for Planning and Execution https://www.linkedin.com/learning/agentic-ai-a-framework-for-planning-and-execution/introduction-to-agentic-ai-avoiding-the-hype Advanced Comparing AI Research Tools: ChatGPT, Claude, Gemini, and Perplexity https://www.linkedin.com/learning/comparing-ai-research-tools-chatgpt-claude-gemini-and-perplexity/choosing-the-right-ai-tool-for-the-job | T2: Basic Learning AI for Business Analysis: https://www.linkedin.com/learning/learning-ai-for-business-analysis/transform-your-business-analysis-career
A3: 1 | B3: 2 | C3: Foundation | D3: Data Literacy | E3: =_xlfn.CONCAT(C3, " - ", D3) -> Foundation - Data Literacy | F3: This competency defines the capacity to read, analyze, and argue with data, transforming raw metrics into evidence-based decisions. It also covers tool usage and the responsibilities and mindset regarding data quality, including the own role and responsibilities in maintaining a high quality data landscape. It includes reading reports and dashboards accurately, understanding basic statistical concepts, recognizing data limitations, and questioning and critically evaluate how data is collected, analyzed, and presented. Employees must demonstrate the ability to identify common logical fallacies, such as conflating correlation with causation, and recognize the limitations of specific datasets, including selection bias and sampling errors. The goal is to foster a data-driven culture where decisions are informed by evidence, assumptions are questioned constructively, and both internal and client discussions are grounded in realistic interpretation of data. | G3: The employee effectively consumes standard reports and understands fundamental statistical concepts necessary for daily operations. Descriptive Statistics: Correctly interprets and understands basic statistical concepts such as mean, median, mode and spread (range), distinguishing between them in reporting. Visual Literacy: Accurately reads standard organizational charts (bar, line, pie) and dashboards without misinterpreting the scale or axes. Data Hygiene: Adheres to basic data entry standards to ensure integrity and understands the direct impact data quality on reports or AI. Tools Usage: Understands how and when to use common LHIND tools (Excel, PowerBI, Data Entry tools) to retrieve and explore information Outcome: Can independently monitor KPIs and operational metrics; understands the "what" of the data presented in team meetings. | H3: The employee actively analyzes data to find patterns and questions the validity of the information presented. Statistical Reasoning: Understands concepts of distribution and variance; distinguishes between simple correlation and causality. Critical Scrutiny: Identifies misleading visualizations (e.g., truncated axes, cherry-picked timeframes) and questions the context of the data (e.g., "Is the sample size n sufficient?"). Contextualization: Connects disparate data points to form a coherent narrative, identifying outliers or anomalies that require investigation rather than dismissal. Understands data requirements for analytics and AI initiatives Tools Usage: Uses advanced features of BI/Analytics tools or AI assisted analysis Outcome: Detects flaws in proposals based on weak data; asks "Why?" and "How was this measured?" during presentations; prevents teams from acting on statistical noise. | I3: The employee evaluates the methodology behind data generation and enforces high standards of epistemic rigor. Methodological Critique: scrutinizes the data collection process itself, identifying systemic biases (e.g., survivorship bias, selection bias) that invalidate the dataset. Probabilistic Thinking: Evaluates risks and forecasts using probabilistic frameworks (e.g., confidence intervals, scenarios) rather than demanding deterministic certainty. Data Strategy: Defines the metrics that should be measured to track strategic goals, ensuring they do not create perverse incentives (Goodhart’s Law). Advises on data tool selection, architecture, and integration with AI systems Outcome: Sets the standard for truth within the department; acts as a gatekeeper against "vanity metrics"; ensures major strategic decisions are backed by statistically sound evidence. | J3: What: Datenarten, Bias, Korrelation vs Kausalität, Understand Data Importance, output validation, source checking Why: Evidenzbasierte Arbeit, realistic expectations. | K3: Expert | L3: Expert | M3: Expert | N3: Advanced | O3: Advanced | P3: Advanced | Q3: Advanced | S3: Basic Data-Backed Decision Making https://www.linkedin.com/learning/data-backed-decision-making/making-better-decisions
A4: 1 | B4: 3 | C4: Foundation | D4: Personal AI Productivity | E4: =_xlfn.CONCAT(C4, " - ", D4) -> Foundation - Personal AI Productivity | F4: This competency defines the individual’s ability to leverage AI tools to improve personal output, optimize time management, and streamline cognitive workflows. It moves beyond mere tool awareness and to the application of Large Language Models (LLMs) and automation software for drafting, summarizing, coding, or problem-solving (among others). It includes effective prompting, iterative refinement of AI-generated content (Human in the loop), responsible handling of sensitive information, and thoughtful judgment about when AI support is appropriate. Crucially, this competency includes the judgment to discern when to use AI versus manual effort, preventing the "time-sink" of over-engineering simple tasks. The objective is to transform the employee from a passive user into an "AI-augmented professional," capable of delivering higher-value work by offloading routine cognitive load to digital assistants while maintaining full accountability for the final quality. | G4: The employee uses AI as a "better search engine" or basic drafter for standalone tasks. Prompting Basics: Formulates simple, zero-shot queries (e.g., "Draft an email to X about Y") but may accept generic outputs without much refinement. Task Application: Uses approved tools for low-risk summarization of long documents or to brainstorm initial ideas for projects. Is aware of applications and use cases in everyday work Validation: Manually reviews AI output for hallucinations or factual errors before using it, treating the AI as a junior intern whose work needs checking. Outcome: Saves time on administrative drafting and reading; reduces the "blank page" problem. | H4: The employee engages in "Chain-of-Thought" reasoning with the AI, integrating it deeply into complex workflows. Advanced Prompting: Uses techniques like "Few-Shot Prompting" (providing examples) and role-setting (e.g., "Act as a Senior Financial Analyst...") to guide the AI toward specific formats and tones. Iterative Refinement: Does not settle for the first result; engages in a multi-turn dialogue to refine, critique, and polish the output. Context Management: Knows how to safely feed relevant context (anonymized data, project background) into the tool to get highly specific, actionable results. Outcome: Produces higher quality work faster; uses AI to critique their own logic or simulate counter-arguments before meetings. | I4: The employee builds personal systems and custom tools that automate repetitive cognitive loops Customization: Configures "Custom Instructions" or builds personal "GPTs/Agents" pre-loaded with specific project knowledge, style guides, and formatting rules. Workflow Chaining: Connects AI tools with other software (e.g., using scripts or integrations) to automate multi-step processes (e.g., "Summarize meeting notes -> extract action items -> draft Jira tickets"). Prompt Library: Maintains and shares a library of high-efficacy prompts for the team, effectively acting as a productivity multiplier for others. Outcome: Operates at a significantly higher velocity than peers; eliminates administrative drudgery entirely; creates reusable assets that benefit the wider team. | J4: What: GenAI für Emails, Kalender, Summaries, M365, Async Work, Collab-Tools. Why: Individuelle Effizienzsteigerung, Effizienz in verteilten Teams. | K4: Expert | L4: Expert | M4: Expert | N4: Basic | O4: Expert | P4: Advanced | Q4: Expert
A5: 1 | B5: 4 | C5: Foundation | D5: Corporate Ethics & Compliance | E5: =_xlfn.CONCAT(C5, " - ", D5) -> Foundation - Corporate Ethics & Compliance | F5: This competency defines the moral, legal, and ethical guardrails for responsible digital and AI usage within the organization. It requires a solid understanding of regulatory frameworks (e.g., GDPR, EU AI Act) and internal compliance rules, combined with the ability to identify and mitigate ethical risks such as bias, lack of transparency, misuse of data, or automation errors. Beyond knowing what is legally permitted, employees act with intention and accountability, carefully considering impacts on people, the organization, and society—especially in ambiguous or complex situations. Technical feasibility alone is not sufficient; decisions must balance innovation with fairness, dignity, and long‑term trust. Mastery of this competency strengthens stakeholder confidence, reduces legal and reputational risks, and safeguards the organization’s license to operate in a highly regulated environment. | G5: The employee acts with fundamental sensitivity, focusing on compliance and adherence to established guidelines. Compliance: Deploys technology, data, and AI in strict accordance with applicable guidelines and regulations. Guardrail Awareness: Knows and respects relevant legal, corporate-specific, and cultural boundaries. Risk Reflection: Reflects on obvious risks and impacts on users and stakeholders (e.g., "Is this data sensitive?"). Consultation: Actively seeks guidance and consultation in cases of uncertainty rather than making assumptions. Outcome: Acts responsibly within their own area of tasks; demonstrates basic ethical sensitivity and rule-conforming behavior | H5: The employee engages in context-aware weighing of options and assumes proactive responsibility for outcomes. Impact Evaluation: Systematically assesses the effects of technology deployment on people, the organization, and society. Risk Detection: Proactively identifies potential risks regarding bias, data privacy, or fairness within workflows or models. Ethical Decision Making: Makes ethically reflected decisions even when faced with conflicting goals (e.g., balancing Speed vs. Fairness). Advocacy: Actively brings ethical aspects into project planning and discussions; promotes the transparent and responsible use of data and AI. Outcome: Acts reflectively and assumes responsibility beyond their immediate role; prevents ethical debt. | I5: The employee exercises systemic responsibility, shaping standards that build long-term trust. Strategic Anticipation: Anticipates the long-term societal and organizational implications of technological decisions. Governance Design: Develops and establishes ethical guidelines, standards, or governance models for the organization. Balanced Strategy: Strategically balances the triangle of Innovation, Economic Viability, and Responsibility. Cultural Leadership: Fosters a culture of integrity, transparency, and sustainability; acts as a role model for responsible technology use. Outcome: actively designs responsible value creation chains; strengthens organizational trust and "Social License to Operate." + protects the brand's ethical reputation against systemic failures (aus 3). | K5: Advanced | L5: Advanced | M5: Expert | N5: Expert | O5: Advanced | P5: Advanced | Q5: Expert
A6: 1 | B6: 5 | C6: Engineering | D6: AI Systems and Architecture | E6: =_xlfn.CONCAT(C6, " - ", D6) -> Engineering - AI Systems and Architecture | F6: This competency defines the technical fluency required to understand how AI solutions are architected, integrated, and deployed within an enterprise environment. It moves beyond the theoretical understanding of algorithms to the practical reality of systems engineering. This includes a grasp of the end-to-end data pipeline—from ingestion and pre-processing to model training (or fine-tuning) and final inference. Employees must understand critical architectural concepts such as APIs, cloud vs. on-premise infrastructure, latency requirements, and the distinct roles of components like Vector Databases or Orchestration layers. The goal is to demystify the "Black Box" of AI, enabling employees to assess technical feasibility, anticipate integration challenges with legacy systems, and make informed decisions regarding "Build vs. Buy." This literacy ensures that projects are scoped realistically, with a clear understanding of the computational resources and maintenance overhead required for production-grade systems. | G6: The employee can identify the major building blocks of an AI system and understands standard technical vocabulary. Vocabulary: Correctly defines terms like "API" (Application Programming Interface), "Inference" (running the model), "Latency" (speed), and "Cloud Computing." System Boundaries: Recognizes that an AI model is not a standalone app but a component that must talk to other systems (e.g., "The Chatbot needs to read the SharePoint database"). Resource Awareness: Understands that AI processes consume computing power (GPU/CPU) and that this translates directly to operational costs. Outcome: Can follow technical updates from IT; understands why a "simple change" might require significant backend work. | H6: The employee understands how data moves through the system and the dependencies between different components. Pipeline Logic: Maps the flow of information: $Input -> Preprocessing -> Model -> Postprocessing -> Output. Understands where errors can occur at each stage. Integration Constraints: Identifies potential bottlenecks (e.g., "If the API is slow, the user waits") and data privacy boundaries (e.g., "Does data leave our secure cloud environment?"). Lifecycle Awareness: Recognizes that deploying a model is just the beginning; understands the need for monitoring and updates (MLOps concepts). Outcome: Can scope projects effectively; identifies missing technical prerequisites (e.g., "We can't use this AI tool because we don't have an API for that data source"). | I6: The employee evaluates technical designs against business goals, optimizing for cost, performance, and reliability. Trade-off Analysis: Balances conflicting constraints, such as Accuracy vs. Latency or Cost vs. Privacy. Makes decisions on "Edge AI" (running on device) vs. "Cloud AI." Scalability: Assesses whether a proposed architecture can handle 10 users or 10,000 users, identifying single points of failure. Technical Debt: Critiques architectural choices that solve an immediate problem but create long-term maintenance burdens (e.g., hard-coding rules instead of using a flexible model). Outcome: Validates vendor technical proposals; challenges IT on over-engineered or under-resourced solutions; ensures the "Total Cost of Ownership" (TCO) is understood before build begins. | J6: What: Models vs Apps, RAG, system components, model lifecycle awareness, frameworks, orchestraction tools, AI Services Why: Defining solutions, realistic thinking, Solution architecture | K6: n. a. | L6: Basic | M6: Expert | N6: n. a. | O6: n. a. | P6: n. a. | Q6: n. a. | S6: Basic Agentic AI for Developers: Concepts and Application for Enterprises https://www.linkedin.com/learning/agentic-ai-for-developers-concepts-and-application-for-enterprises/building-your-own-ai-agent Advanced Agentic AI Fundamentals: Architectures, Frameworks, and Applications https://www.linkedin.com/learning/agentic-ai-fundamentals-architectures-frameworks-and-applications/agentic-ai-the-future-of-smart-ai-is-here
A7: 1 | B7: 6 | C7: Engineering | D7: Agentic Software Development | E7: =_xlfn.CONCAT(C7, " - ", D7) -> Engineering - Agentic Software Development | F7: This competency defines the paradigm shift from "writing code" to "orchestrating development." It entails the ability to effectively utilize autonomous AI agents to execute engineering tasks—ranging from scaffolding new features to refactoring legacy modules. The core skill is no longer syntax memorization, but Intent Specification: the ability to clearly articulate technical requirements and constraints (context) that an agent can execute. Crucially, this requires a rigorous Verification Mindset—the ability to review, audit, and debug machine-generated code with the same scrutiny applied to a junior human developer. It involves managing the "Context Window" (knowing which files to feed the agent) and guiding the agent through iterative error correction. The objective is to elevate the developer from a "typist" to an "Architect," where the human focuses on system design, security, and business logic, while the agent handles implementation details and boilerplate. | G7: The developer uses agents to accelerate isolated, well-defined coding tasks. Scoped Prompting: Can delegate single-file tasks to an agent (e.g., "Write a unit test for this function," "Refactor this method to be async"). Code Review: Reads every line of agent-generated code to ensure it actually runs and follows basic style guidelines before committing. Hallucination Check: Recognizes when an agent invents a library or method that doesn't exist and manually corrects it. Outcome: Eliminates boilerplate work; speeds up unit testing and documentation; maintains code quality in individual files. | H7: The developer guides an agent through multi-step, multi-file changes to implement complete features. Context Engineering: Curates the correct set of files, documentation, and types to feed the agent so it "understands" the broader system architecture before coding. Iterative Steering: Engages in a dialogue with the agent to refine behavior (e.g., "That solution broke the login flow; try again using the AuthService class"). Debugging Agent Logic: Identifies why an agent failed (e.g., "It didn't see the interface definition") and provides the missing information rather than rewriting the code manually. Outcome: Delivers full features faster; effectively uses agents to refactor code across multiple dependencies; reduces "context switching" fatigue. | I7: The developer treats the agent as a "Senior Pair Programmer," using it for high-level design and complex migrations. Architectural Prompts: Asks the agent to propose high-level designs or folder structures before writing code, validating the approach against system constraints. Large-Scale Refactoring: Orchestrates agents to perform tedious, system-wide changes (e.g., "Migrate all API calls from REST to GraphQL") while managing the risk of regression. Security Auditing: specifically prompts agents to audit their own code for vulnerabilities (e.g., "Review your last output for SQL injection risks") and verifies the findings. Outcome: Acts as a "Technical Lead" for an AI workforce; builds prototypes in hours, not days; maintains high architectural integrity despite the speed of generation. | J7: What: Nutzung von (Git) Copilot, Cursor, Ghostwriter, Probabilistisch vs Deterministisch, Logik Why: Entwickler-Produktivität, | K7: Basic | L7: Basic | M7: Expert | N7: Basic | O7: n. a. | P7: n. a. | Q7: n. a. | S7: Basic Agentic AI Fundamentals: Architectures, Frameworks, and Applications https://www.linkedin.com/learning/agentic-ai-for-developers-concepts-and-application-for-enterprises/building-your-own-ai-agent AI and Developer Productivity https://www.linkedin.com/learning/ai-and-developer-productivity/ai-and-developer-productivity The AI Ecosystem for Developers: Models, Datasets, and APIs https://www.linkedin.com/learning/the-ai-ecosystem-for-developers-models-datasets-and-apis/getting-started-with-the-ai-ecosystem
A8: 1 | B8: 7 | C8: Engineering | D8: AI-Driven Testing & QA | E8: =_xlfn.CONCAT(C8, " - ", D8) -> Engineering - AI-Driven Testing & QA | F8: This competency defines the strategic application of AI to the quality assurance process, marking a shift from manual verification to intelligent, automated validation. It moves beyond traditional "scripted" testing (where humans write every step) to understanding how AI tools can autonomously generate test cases, detect anomalies, and "self-heal" broken tests when software updates occur. For employees, this literacy involves recognizing that AI is a force multiplier for speed and coverage, not a magic wand that eliminates the need for human oversight. It requires distinguishing between deterministic checks (is A + B = C?) and probabilistic AI validation (does this look right?). The objective is to transition the organization from reactive "bug catching" to proactive "quality engineering", where AI predicts risk areas and optimizes testing scope, ensuring faster release cycles without compromising stability or compliance. | G8: The employee understands the vocabulary of modern QA and the fundamental difference between manual and AI-assisted testing. Core Concepts: Distinguishes between Manual Testing, Traditional Automation (scripts), and AI-Driven Testing (autonomous). Vocabulary: Correctly uses terms like "Regression Testing" (checking old features still work), "False Positives" (AI flagging a bug that isn't real), and "Test Coverage." Limitations: Recognizes that AI cannot validate "Business Intent" (e.g., the software works technically, but does it solve the user's problem?). Outcome: Can discuss project timelines realistically, understanding that "AI Testing" still requires setup and review time; does not expect zero bugs immediately. | H8: The employee identifies where to apply AI tools to optimize the testing process and reduce bottlenecks. Strategic Application: Identifies high-value use cases for AI, such as "Visual Regression" (spotting UI changes) or "Test Data Generation" (creating fake user data for privacy compliance). Self-Healing Awareness: Understands the value of "Self-Healing" tests (AI that fixes the script when a button name changes) in reducing maintenance costs. Shift Left: Advocates for testing earlier in the development cycle ("Shift Left"), using AI to scan requirements or code drafts before the product is fully built. Outcome: Prioritizes testing resources effectively; evaluates tool vendors based on "maintenance effort" rather than just "creation speed"; writes clear acceptance criteria that AI can validate. | I8: The employee designs the comprehensive Quality Strategy, balancing speed, cost, and risk in an AI-native environment. Risk-Based Testing: Uses AI metrics to predict which parts of the software are most likely to fail (based on code changes) and focuses testing efforts there. Data Governance: Manages the complex compliance issues of "Test Data Management" (TDM), ensuring AI doesn't train on or expose sensitive PII during testing. Algorithmic Integrity: Audits the AI testing tools themselves to ensure they aren't "hallucinating" success (passing a broken feature) or creating "Flaky Tests" (random failures). Outcome: transform the QA function from a cost center to a speed enabler; defines the organization's "Definition of Done"; ensures reliability in continuous delivery pipelines. | J8: What: Test-Genierung, Synthetische Daten. Why: Code-Qualität und Speed. | K8: n. a. | L8: Basic | M8: Expert | N8: Advanced | O8: n. a. | P8: n. a. | Q8: n. a. | S8: Basic Advanced AI-Powered Software Development: Coding, Testing, and System Design https://www.linkedin.com/learning/ai-powered-software-development-coding-testing-and-system-design/code-generation-and-completion-what-are-my-options
A9: 1 | B9: 8 | C9: Engineering | D9: AI-Supported Code Modernization | E9: =_xlfn.CONCAT(C9, " - ", D9) -> Engineering - AI-Supported Code Modernization | F9: This competency defines the strategic ability to leverage AI for transforming legacy systems into modern, maintainable, and secure software. It moves beyond the concept of "rewriting code" to understanding how AI accelerates the refactoring process—translating outdated languages (e.g., COBOL to Java), updating libraries, and documenting "Black Box" systems where original developers have long since left. For employees, this means grasping that "Modernization" is not just a technical upgrade but a risk reduction strategy. It involves recognizing that AI tools can analyze vast codebases to map dependencies, identify security vulnerabilities, and generate test cases for behavior that was previously undocumented. The objective is to enable the organization to pay down "Technical Debt" efficiently, ensuring that critical business operations are not reliant on fragile, obsolete technology. | G9: The employee understands the business risks of legacy code and the basic role AI plays in mitigating them. Vocabulary: Correctly defines terms like "Technical Debt" (cost of rework), "Refactoring" (improving structure without changing function), and "Legacy Code" (old, valuable, but hard to change). AI Role: Recognizes that AI helps assist developers in understanding old code, not just magically rewriting it perfectly. Documentation: values the ability of AI to generate documentation for undocumented systems, reducing the "Key Person Risk" (what happens if the expert leaves?). Outcome: Can articulate the business case for modernization projects; understands why "keeping the lights on" costs increase over time. | H9: The employee actively manages the modernization process, ensuring AI outputs are validated and risks are controlled. Conversion Logic: Understands the difference between a direct "Line-by-Line" translation (often bad) and "Idiomatic Refactoring" (writing code the way a modern developer would). Testing Necessity: Insists on rigorous regression testing; realizes that if the old code had a bug, the AI might faithfully copy that bug into the new language. Scope Management: Identifies which parts of a system are "High Risk/Low Value" (candidates for retirement) vs. "High Risk/High Value" (candidates for AI modernization). Outcome: Drafts realistic project roadmaps; allocates time for "Human Review" of AI-generated code; prioritizes modules for modernization based on business criticality. | I9: The employee orchestrates large-scale systemic changes, balancing architectural purity with business continuity. Architectural Decoupling: Strategies how to break a "Monolith" (one giant program) into "Microservices" using AI to identify logical seams and boundaries. Pattern Recognition: Uses AI to scan the entire codebase for recurring anti-patterns or security flaws, applying fixes at scale rather than one by one. Vendor & Tool Governance: Evaluates the efficacy of specific modernization agents/tools; ensures that proprietary code isn't leaking into public models during the refactoring process. Outcome: Leads the "Strangler Fig" strategy (gradually replacing the old system); quantifies the ROI of modernization (e.g., "We reduced deployment time by 50%"); safeguards the organization's intellectual property. | J9: What: Code-Erklärung, Refactoring mit KI, z.B. für Legacy Systeme. Why: Modernisierung beschleunigen. | K9: Basic | L9: Basic | M9: Expert | N9: Expert | O9: n. a. | P9: n. a. | Q9: n. a.
A10: 1 | B10: 9 | C10: Engineering | D10: AI-Assisted Documentation | E10: =_xlfn.CONCAT(C10, " - ", D10) -> Engineering - AI-Assisted Documentation | F10: This competency defines the ability to leverage AI to solve one of the most persistent challenges in any organization: the "Knowledge Silo." It moves beyond simply writing reports to understanding how AI can dynamically generate, update, and query technical documentation from the underlying systems (code, databases, workflows). For non-engineers, this means the ability to use AI tools to "interrogate" a system and extract plain-language explanations of how it functions ("Reverse Engineering" business rules). It also encompasses the strategy of "Documentation as Living Knowledge"—ensuring that as software or processes change, the corresponding documentation is updated automatically or semi-automatically. The objective is to reduce "Key Person Risk" (where knowledge lives only in one person's head) and ensure that business decisions are based on how the systems actually work, not how they were described three years ago. | G10: The employee knows that documentation can be generated on-demand and how to query it. Retrieval Literacy: Instead of saying "I can't find the manual," the employee uses AI search tools ("Chat with your Data") to find answers within technical repositories. Concept Awareness: Understands that "Code Comments" and "Readme files" exist and that AI can translate these into business-readable summaries. Staleness Detection: Recognizes that if the AI is reading a file from 2021, the answer is likely wrong ("Hallucination by Outdated Context"). Outcome: Can independently answer basic functional questions about internal tools without emailing the engineering team. | H10: The employee actively uses AI to bridge the gap between technical reality and business process. Business Logic Extraction: Uses AI to read code snippets or technical specs and extract the actual business rules (e.g., "According to the code, the discount is applied before tax, not after"). Gap Analysis: Compares the AI-generated description of the system against the official SOPs to find discrepancies ("The system does X, but our policy says Y"). Drafting Assistance: Uses AI to draft technical requirements or bug reports that engineers can actually use, minimizing back-and-forth. Outcome: Acts as a translator between IT and Business; ensures that process maps reflect technical reality; reduces "requirements churn." | I10: The employee treats documentation as a strategic asset and enforces systems to keep it alive. Knowledge Architecture: Designs the flow of information, ensuring that AI tools have access to the "Single Source of Truth" and are blocked from reading deprecated drafts. Docs-as-Code Strategy: Champions the engineering practice where documentation is treated like software (versioned, reviewed, and automated), ensuring business continuity. Legacy Archeology: Leads initiatives to document "Black Box" legacy systems using AI, effectively recovering lost institutional knowledge before a crisis occurs. Outcome: Mitigation of "Bus Factor" (risk of losing key staff); audits and approves the information architecture; ensures the organization remains compliant and auditable. | J10: What: Auto-Docu, Tech-Writing mit KI. Why: Wartbarkeit und Wissenstransfer. | K10: Advanced | L10: Advanced | M10: Expert | N10: Expert | O10: n. a. | P10: Advanced | Q10: Basic
A11: 1 | B11: 10 | C11: Engineering | D11: Sustainable Software & Green Coding | E11: =_xlfn.CONCAT(C11, " - ", D11) -> Engineering - Sustainable Software & Green Coding | F11: This competency defines the practice of designing, building, and maintaining software that is energy-efficient by default. It moves beyond high-level operational metrics (GreenOps) to the granular level of Green Coding—understanding how specific algorithms, languages, and architectural patterns directly dictate physical energy consumption. It requires a semi-formal understanding of "Energy Proportionality" (ensuring systems consume energy only when delivering value) and the ability to optimize code not just for speed, but for carbon intensity. The competency encompasses efficient data handling (minimizing payload sizes), resource-aware logic (avoiding "polling" loops), and the selection of hardware-accelerated libraries. The strategic objective is to embed sustainability as a core "Non-Functional Requirement" alongside security and scalability, ensuring that development teams minimize the carbon footprint of their code before it ever reaches production. | G11: The developer understands the physical connection between code execution and energy consumption. Carbon Literacy: Correctly defines the relationship between software intensity and hardware power draw (Energy = Power x Time). Bloat Recognition: Identifies "Zombie Resources" (unused containers/VMs) and inefficient data practices (e.g., retrieving all columns in a SQL query when only one is needed). Principles: Adheres to the basic tenets of the Green Software Foundation, such as "Carbon Efficiency" (least amount of carbon possible) and "Hardware Efficiency" (using the least amount of embodied carbon). Outcome: Avoids obvious waste; writes clean, concise code that doesn't unnecessarily tax the CPU or memory. | H11: The developer actively profiles and refactors code to reduce computational cost and energy usage. Algorithmic Efficiency: Evaluates code complexity (Big O notation) to select algorithms that minimize CPU cycles (e.g., choosing O(n log n) sorting over O(n^2)), directly reducing energy burn. Data Minimization: Optimizes network payloads (compression, efficient formats like Parquet vs. CSV) to reduce data transfer energy. Resource Management: Implements "Sleep" states and efficient event-driven patterns (e.g., Webhooks) instead of continuous polling loops that keep processors active. Outcome: Delivers software that is leaner and faster; identifies "hot spots" in the code that are disproportionately energy-intensive and refactors them. | I11: The developer architects systems that dynamically adapt to energy availability and grid intensity. Carbon-Aware Computing: Designs systems capable of "Temporal Shifting" (running heavy batch jobs only when the grid is green/renewable) and "Spatial Shifting" (routing workloads to data centers in cooler climates or greener grids). Architectural Efficiency: Makes strategic trade-offs between Microservices (flexibility) and Monoliths (efficiency), recognizing that the network overhead of microservices can increase total energy cost. Measurement & Telemetry: Builds "Software Carbon Intensity" (SCI) metrics directly into the CI/CD pipeline, enabling the team to fail a build if the carbon footprint exceeds a defined threshold. Outcome: Builds "Net Zero" ready systems; sets the standard for sustainable engineering practices; creates feedback loops where energy efficiency drives architectural innovation. | J11: What: Energie-Footprint von KI/Cloud, Efficiency considerations Why: ESG-Ziele der Kunden | K11: Advanced | L11: Advanced | M11: Advanced | N11: Basic | O11: n. a. | P11: n. a. | Q11: Basic | S11: Basic DevOps Best Practices for Sustainability in the Cloud https://www.linkedin.com/learning/devops-best-practices-for-sustainability-in-the-cloud/sustainable-practices-for-growth-and-impact-in-devops
A12: 1 | B12: 11 | C12: Product and Process | D12: AI-Augmented Requirement Engineering | E12: =_xlfn.CONCAT(C12, " - ", D12) -> Product and Process - AI-Augmented Requirement Engineering | F12: This competency defines the strategic integration of AI into the product definition lifecycle, transforming how business needs are captured, analyzed, and translated into technical specifications. It entails leveraging Natural Language Processing (NLP) tools to assist in eliciting, structuring, and refining requirements, ensuring they are unambiguous, consistent, and testable. Employees must understand how to use AI to synthesize unstructured inputs (e.g., meeting transcripts, emails) into formal artifacts like User Stories, Use Cases, or Gherkin syntax (Given -> When -> Then). Crucially, it involves a rigorous "Human-in-the-Loop" validation process to detect logical gaps or "hallucinated" features that the AI might introduce. The objective is to reduce the "Cone of Uncertainty" early in the project, minimizing costly rework caused by misunderstood requirements and ensuring a precise alignment between business intent and engineering execution. | G12: The employee uses AI to speed up the writing of standard requirement documents and ensure basic clarity. Drafting: Generates initial drafts of User Stories or functional requirements from rough bullet points (e.g., "Turn these notes into a standard JIRA ticket format"). Standardization: Uses AI to enforce a consistent tone and structure across documents, ensuring all requirements follow the "INVEST" criteria (Independent, Negotiable, Valuable, Estimable, Small, Testable). Summarization: Rapidly condenses long stakeholder interview transcripts into key feature requests and pain points. Outcome: Reduces administrative overhead; ensures that tickets and docs are legible and follow the company template. | H12: The employee uses AI to interrogate requirements, finding edge cases and logical inconsistencies before developers see them including AI-Augmented Behavior-Driven Development (BDD), where AI generates Given/When/Then scenarios from natural language requirements. Ambiguity Detection: prompts the AI to act as a "Critical Reviewer," specifically asking it to identify vague terms (e.g., "fast," "user-friendly") that need quantification (e.g., "< 200ms"). Scenario Generation: Uses AI to brainstorm "Edge Cases" and "Unhappy Paths" (e.g., "What happens if the user loses internet connection mid-transaction?") that were missed in the initial scope. Translation: Converts textual requirements into structured formats like Mermaid.js code for diagrams or Gherkin syntax for automated testing.Leverages AI to generate BDD scenarios (Given/When/Then) directly from stakeholder conversations, enabling automated acceptance testing from Day 1. Outcome: Delivers robust, "developer-ready" specifications; proactively identifies gaps in logic; reduces the back-and-forth between Business and IT. | I12: The employee manages the entire requirements ecosystem, ensuring that changes propagate correctly and align with high-level goals. Impact Analysis: Uses AI to trace the downstream impact of a requirement change (e.g., "If we change this login rule, which 5 other modules break?"). Conflict Resolution: Analyzes large sets of requirements from different stakeholders to identify conflicting constraints (e.g., Stakeholder A wants Speed, Stakeholder B wants complex Encryption). Living Specifications: Maintains a dynamic, AI-updated specification repository where requirements auto-sync with code changes, API contracts, and test results – eliminating the 'Rotting Spec' problem entirely. Outcome: Ensures complete traceability from "Business Goal" to "Code Deployment"; manages scope creep effectively using data; aligns product roadmap with technical reality. | J12: What: User Stories & Akzeptanzkriterien via KI. Why: Bessere Spezifikationen, schneller. | K12: Expert | L12: Expert | M12: Advanced | N12: Basic | O12: Basic | P12: Basic | Q12: Basic
A13: 1 | B13: 12 | C13: Product and Process | D13: AI-Enhanced User Research | E13: =_xlfn.CONCAT(C13, " - ", D13) -> Product and Process - AI-Enhanced User Research | F13: This competency defines the capability to leverage AI to accelerate the discovery and synthesis of user insights, transforming raw feedback into actionable product strategy. It moves beyond manual data coding to utilizing Natural Language Processing (NLP) for analyzing vast quantities of qualitative data—such as customer interviews, support tickets, and open-ended survey responses—at scale. Employees must understand how to use AI to identify sentiment, extract recurring themes, and even simulate user reactions via "Synthetic Personas" (while strictly maintaining a clear distinction between real and synthetic data). Crucially, this literacy includes the ability to audit AI-generated insights for bias and hallucination, ensuring that speed does not compromise empathy or accuracy. The objective is to democratize access to user insights, allowing teams to make evidence-based decisions faster and reducing the "Time to Insight" from weeks to hours. A strict ethical boundary must be maintained: synthetic data may inform hypotheses but never replace real user validation for high-stakes decisions. | G13: The employee uses AI to process individual data points faster, reducing the manual drudgery of research. Transcription & Summary: Routinely uses AI tools to transcribe meetings and generate accurate, bulleted summaries of customer interviews immediately after they occur. Sentiment Check: Applies basic sentiment analysis tools to gauge the general "mood" of a batch of feedback (Positive/Negative/Neutral). Searchability: Uses AI-enabled repositories to ask questions of existing research (e.g., "What did customers say about the login button last month?") rather than re-running studies. Outcome: Drastically reduces administrative time; ensures no interview or feedback is "lost" in a folder; democratizes access to basic customer sentiments. | H13: The employee uses AI to connect dots across multiple sources, identifying patterns that humans might miss. Thematic Coding: Uses AI to analyze hundreds of open-ended responses and auto-categorize them into specific themes (e.g., "Pricing," "Usability," "Feature Gap"). Cross-Reference: Prompts AI to look for correlations between disparate datasets (e.g., "Do users who complain about speed also mention the mobile app?"). Voice of Customer Analytics: Uses AI to continuously analyze NPS verbatims, support tickets, and review data to surface emerging themes and churn signals at scale. Gap Analysis: Asks the AI to critique the research plan or interview guide, identifying leading questions or missing demographic perspectives before data collection begins. Outcome: Delivers deeper insights faster; uncovers "Long Tail" issues that manual analysis would ignore; validates hypotheses with broad data support. | I13: The employee uses AI to simulate user behaviors and create continuous, automated research loops. Synthetic Personas: Creates and interacts with "Synthetic Users" (AI modeled on real user data) to test early value propositions or messaging before recruiting human participants. Predictive Insight: Uses AI to forecast future user needs or churn risks based on subtle shifts in language patterns across support channels over time. Bias Auditing: Rigorously tests the AI models themselves for cultural or cognitive bias, ensuring that the "Voice of the Customer" isn't skewed by the training data. Establishes clear governance rules for synthetic persona usage: mandatory labeling of synthetic vs. real data, prohibition of synthetic data in regulatory submissions, and regular validation against real user panels. Outcome: Reduces the risk of product flops by "pre-testing" concepts; creates a "Continuous Discovery" engine that runs 24/7; advises leadership on the ethical limits of synthetic data. | J13: What: Sentiment Analyse, Persona Simulation. Why: Tieferes Kundenverständnis. | K13: Expert | L13: Expert | M13: Basic | N13: n. a. | O13: Basic | P13: Basic | Q13: Basic | S13: Basic Active Listening: The Secret to Effective Communication - What is user research? https://www.linkedin.com/learning/active-listening-the-secret-to-effective-communication/what-is-user-research
A14: 1 | B14: 13 | C14: Advisory and Business Consulting | D14: AI & Automation Use Case Spotting | E14: =_xlfn.CONCAT(C14, " - ", D14) -> Advisory and Business Consulting - AI & Automation Use Case Spotting | F14: This competency defines the strategic ability to identify, qualify, and articulate high-value opportunities for AI and automation within business operations. It requires a diagnostic mindset to deconstruct workflows, pinpoint inefficiencies, and map specific technological solutions to genuine business problems. Employees must move beyond "solutioneering" (finding a problem for a cool tool) to a rigorous assessment of Process Suitability, distinguishing between tasks suitable for deterministic automation (RPA) versus those requiring probabilistic reasoning. It involves applying frameworks like the "Impact vs. Feasibility" matrix to prioritize initiatives based on data availability, risk, and potential ROI. The objective is to foster a culture of "Citizen Innovation," where employees actively reduce operational friction by deploying technology to solve specific bottlenecks—reducing manual toil, accelerating analysis, or scaling personalization—ultimately driving measurable business value. | G14: The employee can spot repetitive, low-value tasks in their immediate environment that are ripe for automation. Pain Point Recognition: Identifies tasks that are "Dull, Dirty, or Dangerous" (in a data sense)—specifically manual data entry, copy-pasting between apps, or scheduling. Taxonomy of Waste: Distinguishes between "Cognitive Load" (thinking) and "Administrative Load" (formatting), recognizing that AI is best suited to reduce the latter first. Problem articulation: Can clearly state the problem (Current State) and the desired outcome (Future State) without necessarily knowing the technical "How." Outcome: Generates a backlog of simple "Quick Win" ideas; stops accepting manual drudgery as "just the way things are." | H14: The employee evaluates the feasibility of an idea, ensuring it is technically viable and economically sensible. Feasibility Check: Asks critical questions before proposing a solution: "Do we have the data?", "Is the process stable?", "Is the error tolerance zero?" (if yes, GenAI might be wrong). Tool Matching: Correctly maps the problem to the solution class: Uses RPA for structured, rule-based tasks (e.g., invoicing) and LLMs for unstructured, creative tasks (e.g., summarizing emails). ROI Estimation: Calculates a rough "Return on Investment" based on hours saved (Hours x Rate) vs. the cost of building/buying the tool. Outcome: Submits high-quality project briefs; filters out "Cool but Useless" ideas; prevents the team from automating broken processes ("Paving the Cow Path"). | I14: The employee looks at the entire value chain to transform how work gets done, rather than just speeding up existing steps. Process Re-engineering: Instead of automating step 3 of a 5-step process, they ask: "If we have AI, do we even need steps 2 and 4?" (e.g., changing "Draft -> Review -> Send" to "Auto-Generate -> Approve"). Portfolio Management: Balances a mix of "Horizon 1" (Incremental efficiency) and "Horizon 2" (Transformative) use cases, managing the aggregate risk and reward. Buy vs. Build Strategy: Makes informed decisions on whether to use off-the-shelf SaaS features or commission custom development based on competitive advantage. Outcome: Drives departmental transformation; reallocates headcount from admin tasks to strategic roles; aligns automation efforts with high-level corporate OKRs. | J14: What: Value vs Hype erkennen beim Kunden, RPA, KI Potentiale erkennen Why: Sales & Consulting Erfolg. | K14: Expert | L14: Advanced | M14: Advanced | N14: Basic | O14: Expert | P14: Basic | Q14: Advanced | S14: Basic Agentic AI for Business Analysis https://www.linkedin.com/learning/agentic-ai-for-business-analysis/why-ai-solutions-need-business-analysis-too
A15: 1 | B15: 14 | C15: Advisory and Business Consulting | D15: AI Cost & Value Economics | E15: =_xlfn.CONCAT(C15, " - ", D15) -> Advisory and Business Consulting - AI Cost & Value Economics | F15: This competency defines the financial acumen required to evaluate Artificial Intelligence not just as a technology, but as an economic engine with distinct cost structures and value drivers. It moves beyond the hype of "productivity" to the rigorous analysis of Unit Economics—understanding the direct cost per transaction (e.g., cost per query, token, or generated image) versus the marginal value created. Employees must grasp the concept of Total Cost of Ownership (TCO) for AI, which includes "invisible" costs like cloud inference, vector storage, continuous monitoring, and human review time, often dwarfing the initial licensing fees. The objective is to empower the organization to avoid "Bill Shock" from unmanaged consumption and to make data-driven decisions on whether a use case is financially viable (Value > Cost), ensuring that AI initiatives drive genuine profitability rather than becoming expensive technical novelties. For consulting, this also includes the ability to design AI pricing models for clients – translating technical cost structures into commercial offerings (per-query pricing, outcome-based models, subscription tiers). | G15: The employee understands that AI usage incurs variable costs and tracks consumption against budget. Cost Drivers: Recognizes that "Asking the AI" is not free; understands the difference between fixed costs (seat licenses) and variable costs (usage/tokens). Vocabulary: Correctly defines terms like "Tokens" (parts of words used for billing), "Inference Cost" (running the model), and "Credits." Budget Tracking: Monitors team usage to ensure they stay within the allocated monthly limits; flags unexpected spikes in consumption immediately. Outcome: Prevents "Zombie Subscriptions" (paying for unused tools); encourages responsible usage among team members. | H15: The employee calculates the specific return on investment for individual use cases. Unit Calculation: Estimates the cost of a single operation (e.g., "Summarizing this 50-page PDF costs approx. $0.30 in tokens"). Value Comparison: Compares the AI cost against the alternative (Human Labor Cost); determines if the efficiency gain justifies the expense (e.g., "Is it worth $0.10 to save 2 minutes of employee time?"). Model Selection: Chooses the most cost-effective model for the task—using a cheaper, faster model (e.g., GPT-3.5/Haiku) for simple sorting, and reserving the expensive "Smart" model (e.g., GPT-4/Opus) only for complex reasoning. Applies cost-performance optimization: selects models not just by capability but by cost-per-task ratio (e.g., routing simple classification to Haiku/Flash while reserving Opus/GPT-4 for complex reasoning). Understands GPU inference cost drivers. Outcome: Justifies budget requests with math; kills "Negative ROI" projects early; optimizes workflows to reduce waste. | I15: The employee manages the economic architecture of the organization's AI portfolio. AI FinOps: Implements governance policies to dynamically manage cloud spend (e.g., "Rate Limiting," "Budget Alarms," "Chargebacks" to specific departments). Build vs. Buy: Conducts sophisticated financial modeling to decide whether to rent a model (API cost) or fine-tune/host an open-source model internally (Infrastructure + Maintenance cost). AI Pricing Design: Architects commercial pricing models for AI-powered services (per-transaction, tiered SLAs, outcome-based), ensuring margin protection while remaining competitive. Understands the economics of 'AI as a Service' vs. 'AI-embedded in Consulting'. CAPEX vs. OPEX: Structures AI investments to align with corporate financial goals (e.g., treating GPU clusters as Capital Expenditure vs. API costs as Operational Expenditure). Outcome: Maximizes the organization's "AI Yield"; negotiates enterprise agreements with vendors; ensures the company’s AI strategy is financially sustainable at scale. | J15: What: Token-Kosten, ROI, TCO von KI, Business Cases berechnen Why: Wirtschaftlichkeit bewerten. | K15: Expert | L15: Advanced | M15: Advanced | N15: Basic | O15: Advanced | P15: Basic | Q15: Expert
A16: 1 | B16: 15 | C16: Advisory and Business Consulting | D16: Consultative Prompting | E16: =_xlfn.CONCAT(C16, " - ", D16) -> Advisory and Business Consulting - Consultative Prompting | F16: This competency defines the advanced ability to engage Artificial Intelligence not merely as a task-execution engine, but as a strategic thought partner. It transcends basic "instructional prompting" (telling the AI what to write) to embrace Consultative Dialogue—a dynamic, iterative process of Socratic questioning, scenario simulation, and multi-perspective analysis. Employees must master the art of contextual framing, assigning the AI specific professional personas (e.g., "Act as a Skeptical CFO" or "Act as a UX Researcher") to stress-test ideas and uncover blind spots. It involves the skill of "Chain-of-Thought" prompting, guiding the model to break down complex business problems into logical steps before delivering a solution. The objective is to elevate the employee’s cognitive capacity, enabling them to use AI to simulate negotiations, critique strategies, and synthesize diverse viewpoints, effectively having a "Board of Advisors" on demand. This extends to AI-assisted workshop facilitation – using AI to prepare client workshops (stakeholder analysis, hypothesis generation, agenda optimization) and to synthesize workshop outputs in real-time. | G16: The employee can structure a prompt to get a specific, high-quality business output. Role Assignment: Consistently assigns a relevant persona to the AI (e.g., "You are an expert Project Manager") to influence the tone and depth of the response. Context Setting: Provides necessary background information (the "Who, What, Where") rather than asking vague, one-sentence questions. Output Formatting: Explicitly requests the desired format (e.g., "Give me a table comparing X and Y," "Write a memo in the style of Amazon's 6-pager"). Outcome: Receives usable first drafts; reduces the need for manual rewriting; avoids generic, "fluffy" AI answers. | H16: The employee treats the AI as a collaborator, engaging in back-and-forth refinement to improve the logic. Socratic Interaction: Asks the AI to "Think step-by-step" or "Explain your reasoning" to uncover the logic behind a recommendation. Counter-Factual Prompting: Ask the AI to challenge the user's own assumptions (e.g., "Critique this plan from the perspective of a competitor," "What are the top 3 reasons this initiative will fail?"). Few-Shot Prompting: Provides examples of "Good" and "Bad" outputs to guide the AI’s performance on complex tasks (e.g., "Here are three examples of how we write executive summaries..."). Workshop Preparation: Uses AI to research client context, generate tailored discussion frameworks, simulate likely client objections, and prepare data-backed talking points before client engagements. Outcome: Refines strategy documents; identifies risks in plans before presenting to leadership; produces nuanced, highly contextualized work products. | I16: The employee designs complex "Prompt Chains" to simulate expert panels or automate high-level reasoning. Multi-Persona Simulation: Orchestrates a debate between multiple AI personas (e.g., "Simulate a conversation between a Privacy Lawyer, a Marketing Director, and a CTO about this new feature"). Recursive Refinement: Sets up a workflow where the AI generates an output, then reviews its own work against a rubric, then improves it (Self-Correction Loop). Prompt Library Design: Creates and maintains a shared library of "Mega-Prompts" (complex, modular instructions) for the department, scaling high-performance behaviors to the team. Outcome: Solves "wicked problems" with diverse inputs; automates complex decision-support workflows; acts as a force multiplier for the team’s strategic thinking. | J16: What: Rollenspiele, Strategie-Entwurf mit KI, Ideation Why: Vorbereitung auf Kunden-Termine. | K16: Expert | L16: Advanced | M16: Advanced | N16: Advanced | O16: Expert | P16: Basic | Q16: Expert | S16: Advanced: - https://www.linkedin.com/learning/prompting-with-agentic-techniques/the-evolution-of-prompting - https://www.linkedin.com/learning/multimodal-prompting-with-google-s-project-gemini/why-project-gemini-is-important - https://www.linkedin.com/learning/advanced-prompt-engineering-techniques/prompting-to-make-ai-systems-more-useful
A17: 1 | B17: 16 | C17: Advisory and Business Consulting | D17: AI Ecosystem Knowledge | E17: =_xlfn.CONCAT(C17, " - ", D17) -> Advisory and Business Consulting - AI Ecosystem Knowledge | F17: This competency defines the strategic awareness of the rapidly evolving Artificial Intelligence marketplace, enabling employees to navigate the complex web of vendors, platforms, and open-source communities. It moves beyond understanding the technology to understanding the industry dynamics—identifying key players (e.g., Hyperscalers vs. specialized startups), distinct ecosystem approaches (Closed/Proprietary vs. Open Weights), and the underlying hardware supply chain (GPU availability). Employees must grasp the trade-offs between "Walled Gardens" (like the OpenAI/Microsoft or Google ecosystems) and flexible, self-hosted solutions (like Meta’s Llama or Mistral). The objective is to equip the organization with the market intelligence to make resilient procurement decisions, avoid dangerous "Vendor Lock-in," and distinguish between genuine infrastructure shifts and fleeting marketing hype. This ensures that the company’s digital strategy relies on sustainable partners rather than "Ghostware" or deprecating platforms. | G17: The employee knows the major entities and the basic categories of the AI market. Key Players: Correctly identifies the "Big Tech" providers (Microsoft/OpenAI, Google, AWS/Anthropic) and major open-source contenders (Meta, Mistral). Category Distinction: Distinguishes between "Foundation Models" (the brain), "Infrastructure" (the chips/cloud), and "Applications" (the tool you use). News Literacy: Can follow industry news and understand the implications of major announcements (e.g., "Why does it matter if a model has a 1 million token context window?"). Outcome: Participates intelligently in strategy discussions; doesn't confuse a software wrapper with a foundation model. | H17: The employee evaluates different ecosystems to select the best fit for specific business needs. Model Nuance: Understands the specific strengths of different model families (e.g., "Claude is often preferred for creative writing and coding," "GPT-4 is strong on reasoning," "Gemini excels at multimodal/video analysis"). Ecosystem Integration: Evaluates how well a tool plays with existing corporate systems (e.g., "Copilot integrates with M365 natively, but using ChatGPT requires data movement"). Open vs. Closed: Articulates the pros and cons of using a proprietary API (fast, easy, but data leaves the premise) vs. hosting an open model (private, control, but high maintenance). Outcome: Advises on tool selection; writes informed RFPs (Request for Proposals); prevents the company from buying redundant tools. | I17: The employee predicts market shifts to position the organization for long-term resilience and leverage. Commoditization Strategy: Recognizes that "Intelligence" is becoming a commodity and advises the business to build value on proprietary data and workflows, not just the model itself. Supply Chain Risks: Analyzes the geopolitical and physical constraints of the AI supply chain (chip shortages, energy limits) and plans for redundancy. Sovereign AI: Develops strategies for "Model Independence," ensuring the organization can switch providers easily if a vendor changes pricing or terms (the "Wrapper Strategy"). Outcome: Defines the 3-5 year technology roadmap; manages high-stakes vendor negotiations; builds the organization's "Moat" against competitors using similar AI tools. | J17: What: Modelle (GPT vs Claude), Player, Trends. Why: Markt-Kompetenz zeigen. | K17: Expert | L17: Advanced | M17: Expert | N17: Basic | O17: Basic | P17: Basic | Q17: Advanced
A18: 1 | B18: 17 | C18: Leadership and Strategy | D18: Managing AI Transformations | E18: =_xlfn.CONCAT(C18, " - ", D18) -> Leadership and Strategy - Managing AI Transformations | F18: This competency defines the strategic capability to orchestrate the complex organizational shift required to thrive in an AI-native environment. It moves beyond the technical implementation of tools to the critical human dynamics of Change Management. Leaders must navigate the "Trough of Disillusionment," managing expectations when initial pilots stall, while simultaneously fostering a culture of psychological safety where experimentation is encouraged and failure is viewed as learning. It involves aligning AI initiatives strictly with core business objectives to avoid "Solutionism" (building tech for tech's sake) and rigorously addressing the "Skills Gap" through targeted upskilling and role redesign. The objective is to guide the organization through the turbulence of disruption—mitigating fears of job displacement while unlocking productivity—ultimately establishing a resilient operating model where human judgment and machine speed are seamlessly integrated. | G18: The leader supports AI initiatives within their immediate scope and models positive adoption behaviors. Change Advocacy: Actively communicates the "Why" behind AI adoption to their team, countering rumors and reducing "FUD" (Fear, Uncertainty, Doubt). Psychological Safety: Creates an environment where team members feel safe to admit they don't know how to use a tool, encouraging peer-to-peer learning. Pilot Participation: Volunteers their team for pilot programs, providing constructive feedback on what works and what doesn't in a real-world setting. Outcome: Reduces friction during rollout; ensures high adoption rates within their specific unit; prevents "passive resistance." | H18: The leader actively redesigns how work gets done to accommodate AI, managing the "dip" in productivity during the transition. Workflow Re-engineering: Identifies that adding AI to a broken process just makes it break faster; proactively redesigns team workflows to leverage automation (e.g., changing "Who writes the first draft"). KPI Adjustment: Shifts performance metrics from "Output Volume" or "Hours Worked" to "Outcome Quality" and "Strategic Value," recognizing that AI distorts old productivity proxies. Skill Gap Management: Conducts skills assessments to identify which team members need training in e.g. Prompt Engineering vs. Data Literacy and allocates budget/time for it. Outcome: Successfully scales pilots into production; manages the "Shadow IT" risk by providing sanctioned paths for innovation; demonstrates tangible efficiency gains. | I18: The leader redefines the business model and operating structure to be "AI-First." Target Operating Model (TOM): Redesigns the organizational chart to reflect new realities (e.g., creating "AI Centers of Excellence" or embedding data scientists into business units). Shapes consulting offerings or delivery models around AI Resource Allocation: Makes hard decisions to sunset legacy projects or roles that are no longer viable, reallocating capital to high-growth AI initiatives (Capital_{AI} > Capital_{Legacy}). Cultural Transformation: Embeds "Continuous Learning" into the DNA of the company, recognizing that the pace of AI change requires a workforce that reinvents itself every 18 months. Outcome: Future-proofs the organization; attracts top technical talent; ensures the company isn't just "doing digital" but is digital; aligns the Board and C-Suite on long-term AI strategy. | J18: What: Change Mgmt, Kultur-Wandel. Why: KI ist ein People-Topic. | K18: Expert | L18: Advanced | M18: Basic | N18: Basic | O18: Expert | P18: Basic | Q18: Advanced
A19: 1 | B19: 18 | C19: Leadership and Strategy | D19: AI Workforce Strategy | E19: =_xlfn.CONCAT(C19, " - ", D19) -> Leadership and Strategy - AI Workforce Strategy | F19: This competency defines the strategic planning required to align human capital with an AI-enabled future. It transcends simple headcount reduction to focus on Workforce Transformation—identifying which roles will be augmented, which will be automated, and what net-new roles (e.g., AI Ethicists, MLOps Engineers) are required. Leaders must rigorously assess the "Half-Life of Skills" of their teams, implementing aggressive upskilling programs to bridge the gap between legacy expertise and digital fluency. It involves the architectural redesign of job descriptions to prioritize judgment, empathy, and complex problem-solving over routine cognitive tasks. The objective is to build a resilient "Human-Centric AI" culture where technology acts as a force multiplier for talent, ensuring the organization attracts and retains the hybrid workforce necessary for sustainable growth while navigating the sensitive ethics of automation-driven displacement. | G19: The leader understands the changing nature of talent and can identify "AI Affinity" within their current team. Encourages a Data / AI Culture Talent Spotting: Identifies employees who show high aptitude for digital tools and "AI Curiosity," tagging them as potential champions rather than just "tech-savvy." Task Analysis: Breaks down team roles into "Tasks" vs. "Jobs," recognizing that while a task (e.g., scheduling) can be automated, the job (e.g., Executive Assistant) might evolve. Skill Literacy: Understands the difference between "Hard Skills" (Python, Prompting) and "Enduring Skills" (Critical Thinking, Negotiation) that AI cannot easily replicate. Outcome: Prevents impulsive/rapid hiring decisions; supports team members who want to experiment; maintains a realistic view of what the current team can achieve with AI. | H19: The leader actively redesigns roles and manages the "Build vs. Bot" trade-off for specific functions. Job Crafting: Rewrites Job Descriptions (JDs) to remove obsolete requirements (e.g., "Must be fast at Excel data entry") and insert AI-relevant competencies (e.g., "Must be able to audit AI outputs"). Capacity Planning: Calculates the "Capacity Release" from automation (e.g., "If AI saves 20% of the team's time, where do we reinvest that 20%?") to prevent idle tim, manage productivity transitions Upskilling Pathways: Designs specific learning journeys for the team (e.g., sending analysts to "Data Literacy" bootcamps), measuring progress against business need, identifies skill gap Outcome: Successfully transitions staff from "Doers" to "Reviewers"; fills open roles by upskilling internal talent rather than expensive external hires; manages the "Hybrid Team" (Humans + Agents). | I19: The leader defines the long-term talent structure, balancing automation economics with human capital sustainability. Strategic Workforce Planning (SWP): Models future headcount scenarios based on AI adoption rates (e.g., "In 3 years, we need 30% fewer Junior Coders but 50% more System Architects"). Build vs. Buy vs. Bot: sophisticatedly evaluates every talent gap: Should we Hire (Buy), Train (Build), or Automate (Bot)? (Cost_{bot} < Cost_{hire}). Ethical Transition: Designs responsible "Offboarding" or "Redeployment" strategies for displaced roles, minimizing reputational risk and maintaining survivor morale. Outcome: Creates a sustainable, high-performance talent ecosystem; attracts top-tier technical leadership; ensures the organization is "Future-Ready" regardless of specific tool changes. | J19: What: Skill-Shift, Neue Rollenbilder. Why: Zukunftsfähigkeit der Org. | K19: Advanced | L19: Basic | M19: Basic | N19: Basic | O19: Basic | P19: Expert | Q19: Expert
A20: 1 | B20: 19 | C20: Leadership and Strategy | D20: Decision Making with AI | E20: =_xlfn.CONCAT(C20, " - ", D20) -> Leadership and Strategy - Decision Making with AI | F20: This competency defines the ability to integrate Artificial Intelligence into the executive decision-making process, moving from purely intuition-based leadership to AI-Augmented Intelligence. It requires the discernment to distinguish between decisions that are suitable for algorithmic optimization (e.g., inventory forecasting, resource allocation) and those demanding human judgment (e.g., ethical dilemmas, complex negotiations). Leaders must master the interpretation of probabilistic outputs, understanding that AI provides predictions based on correlations, not certainties based on causality. Crucially, this literacy involves recognizing and mitigating "Automation Bias" (the tendency to over-rely on computer suggestions) and maintaining strict Human-in-the-Loop accountability for high-stakes outcomes. The objective is to use AI to expand the cognitive scope of the leadership team—processing vast datasets to identify non-obvious options—while retaining the final moral and strategic authority. | G20: The leader uses AI to gather data and challenge their own assumptions but ultimately makes the call manually. Source Criticality: Consults AI summaries or data analysis to inform a decision but verifies the "Source of Truth" before acting (e.g., "The AI says sales are down, let me check the raw CRM report"). Bias Awareness: Recognizes that AI outputs can reflect historical biases in training data and actively questions if a recommendation reinforces a stereotype. Option Generation: Uses AI to brainstorm a "Long List" of potential solutions to a problem, expanding the decision space beyond the team's immediate ideas. Outcome: Makes more well-rounded decisions; reduces "Groupthink" by introducing an external (AI) perspective; avoids "Analysis Paralysis" by getting quick summaries. | H20: The leader uses AI to simulate complex futures and quantifies uncertainty before committing resources. Simulation: Uses AI to run "What-If" scenarios (e.g., "Simulate the P&L impact if supply costs rise by 15% and demand drops by 5%"). Confidence Intervals: Interprets AI predictions not as facts but as ranges (e.g., "The model predicts 80% confidence in this outcome"), creating contingency plans for the other 20%. Constraint Optimization: Uses AI to solve multi-variable problems (e.g., "Optimize the shift schedule for lowest cost while meeting these 5 HR constraints"). Outcome: Justifies strategic bets with robust data modeling; communicates risk more precisely ("We have a high probability of X..."); reduces the cost of failed experiments. | I20: The leader designs the system of authority, deciding what decides (Human vs. Machine). Decision Delegation: Explicitly categorizes decisions into "Type 1" (Reversible/Low Risk $\rightarrow$ Automate with AI) and "Type 2" (Irreversible/High Risk -> Human Decision). Algorithmic Accountability: Establishes the "Rule of Law" for AI decisions—defining who is responsible if the algorithm makes a mistake (e.g., "The Human Manager is always liable"). Feedback Loops: Designs systems where the outcome of every decision (Success/Failure) is fed back into the model, creating a "Learning Organization." Outcome: Increases organizational velocity by automating routine choices; focuses senior leadership attention only on "Edge Cases"; ensures ethical compliance at scale. | J20: What: KI als Sparrings-Partner für Entscheider. Why: Bessere Führungsentscheidungen. | K20: Advanced | L20: Advanced | M20: Basic | N20: Basic | O20: Advanced | P20: Advanced | Q20: Expert
E21: =_xlfn.CONCAT(C21, " - ", D21) -> -

Sheet Mapping
A1: Capability | B1: Profile | C1: Skill-Level | D1: Training

Sheet LHIND Academy Courses
A1: ID | B1: Course | C1: Primary Capability | D1: Primary Role | E1: Format | F1: Driver aus Arbeitskreis | G1: Umsetzer | H1: angefragt | I1: Inhalte
A2: AI-01 | B2: AI: Introduction to GitHub CoPilot | C2: Foundation - Personal AI Productivity | D2: Technology Consulting | E2: LHIND Academy (Blended) | F2: Phillip | G2: Hub Team ASE | H2: ja | I2: in progress
A3: AI-02 | B3: AI: Agentic Software Engineering | C3: Engineering - Agentic Software Development | D3: Technology Consulting | E3: LHIND Academy (Blended) | F3: Lars | G3: Kuratierte Online-Kurs-Liste (Dorina) an Vanesse, Hands-On Session aus OLD von Thomas für Eng | H3: ja
A4: AI-03 | B4: AI: Introduction to Architecture for AI-Systems | C4: Engineering - AI Systems and Architecture | D4: Technology Consulting | E4: LHIND Academy (Blended) | F4: Lars | G4: Kuratierte Online-Kurs-Liste, Georg Reuber als "Kümmerer" | H4: ja
A5: AI-04 | B5: AI: Requirement Engineering with AI | C5: Product and Process - AI-Augmented Requirement Engineering | D5: Business & Strategy Consulting | E5: LHIND Academy (TBD) | F5: Phillip | G5: Idee: Alexander Fülbier / HUB-Team | H5: ja | I5: in progress
A6: AI-05 | B6: AI: AI for Project Managers and Product Owners | C6: Foundation - Digital & AI Terminology, AI Concepts, Tool overviews | D6: Project Management & Agility | E6: LHIND Academy (TDB) | F6: Phillip | G6: Stefan Ebmeyer DONE | H6: ja | I6: liegt intern nicht vor aktuell. Stefan in Ausarbeitung
A7: AI-06 | B7: AI: Introduction to Concepts and Tools for Personal Productivity | C7: Foundation - Personal AI Productivity | D7: All LHIND employees | E7: LHIND Academy (Blended) | F7: Vanessa | G7: Michael Koch (input geber) | I7: Fokus auf LHIND verfügbare/empfohlene Tools, plus online trainings
A8: AI-07 | B8: AI: Introduction to Data-driven Decision Making | C8: Foundation - Data Literacy | D8: Leadership | E8: Online Kurse | F8: Vanessa | G8: Coursera, Online Trainings, Google, Microsoft | I8: Fokus AI Driven decision making,
A9: AI-08 | B9: AI: AI for Leaders | C9: Leadership and Strategy - Managing AI Transformations | D9: Leadership | E9: Online Kurse | F9: Oksana | G9: LinkedIn Trainings
A10: AI-09 | B10: AI Fundamentals / AI for Everyone | C10: Foundation - Digital & AI Terminology, AI Concepts, Tool overviews | D10: All LHIND employees | E10: Online Kurse | F10: Oksana | G10: Coursera, LinkedIn Trainings, Microsoft

Sheet Trainings
A1: LHIND Academy Training | B1: Module ID | C1: Titel | D1: Primary Role | E1: Provider | F1: Module/Course Name | G1: Module Course Content Summary | H1: Format | I1: Cost | J1: URL | K1: Status | L1: LHIND Academy Kurs ja /nein
A2: AI-06 | B2: AI-06-01 | C2: =VLOOKUP(A2,'LHIND Academy Courses'!$A$1:$F$10,2,FALSE) -> AI: Introduction to Concepts and Tools for Personal Productivity | D2: All LHIND employees | E2: Microsoft Learn | F2: AI for Business Users (Use AI for everyday tasks) | G2: Hands-on generative AI for daily productivity: prompting, writing, summarizing, ideation, responsible AI usage. | H2: Self-paced online (~1-2 hour) | I2: Free | J2: https://learn.microsoft.com/de-de/training/paths/ai-fluency/ | K2: Link überprüfen (führt zu keinem konkreten Kurs)
A3: AI-06 | B3: AI-06-02 | C3: =VLOOKUP(A3,'LHIND Academy Courses'!$A$1:$F$10,2,FALSE) -> AI: Introduction to Concepts and Tools for Personal Productivity | D3: All LHIND employees | E3: Google / Coursera | F3: Google AI Fundamentals | G3: Using AI as a professional work assistant, prompt frameworks, evaluating output quality, bias awareness. | H3: Self-paced online (~3 hours) | I3: Coursera subscription | J3: https://www.coursera.org/learn/google-ai-fundamentals | K3: Sharepoint gepflegt
A4: AI-06 | B4: AI-06-03 | C4: =VLOOKUP(A4,'LHIND Academy Courses'!$A$1:$F$10,2,FALSE) -> AI: Introduction to Concepts and Tools for Personal Productivity | D4: All LHIND employees | E4: Coursera | F4: Real-World AI for Everyone | G4: [Optional] Claude focused. Fokus auf praktische Nutzung von AI Assistants wie Claude im Berufsalltag: Kommunikation, Dokumente, Analysen, Workflows und Zusammenarbeit mit AI. | H4: Ca. 6-10 h | I4: Free | J4: Real-World AI for Everyone | Coursera | K4: Sharepoint gepflegt
A5: AI-06 | B5: AI-06-04 | C5: =VLOOKUP(A5,'LHIND Academy Courses'!$A$1:$F$10,2,FALSE) -> AI: Introduction to Concepts and Tools for Personal Productivity | D5: All LHIND employees | E5: LHIND | F5: Introduction to LHIND tools and best practices | G5: Introduction to LHIND available tools, LHIND/LHG guidelines and best practices | H5: Instructor-led, ~2-3h | J5: TBD | K5: *- smart assistsant - copilot - Claude Code - Kein Kurs aktuell | L5: 1 Stunde Überblick 2 (1,5h) Hands on LHIND AI Skills | M5: 2-3Trainer suchen, Mark
A6: AI-07 | B6: AI-07-01 | C6: =VLOOKUP(A6,'LHIND Academy Courses'!$A$1:$F$10,2,FALSE) -> AI: Introduction to Data-driven Decision Making | D6: Leadership | E6: Coursera | F6: AI‑Augmented Decision‑Making for Business Leaders | G6: AI-supported decision making, forecasting, bias, uncertainty, ethics, and leadership accountability. | H6: ~ 4h | I6: Free | J6: https://www.coursera.org/learn/ai-augmented-decision-making-for-business-leaders | K6: Sharepoint gepflegt
A7: AI-07 | B7: AI-07-02 | C7: =VLOOKUP(A7,'LHIND Academy Courses'!$A$1:$F$10,2,FALSE) -> AI: Introduction to Data-driven Decision Making | D7: Leadership | E7: Coursera | F7: AI Powered Decision Making | G7: [Optional] Fortgeschrittener Kurs zu AI-gestützten Entscheidungsmodellen, Predictive Analytics, Automatisierung und intelligenten Decision Frameworks. | H7: ~34h | I7: Free | J7: AI-Powered Decision Intelligence | Coursera | K7: gleicher Kurs unter AI-08-04
A8: AI-08 | B8: AI-08-01 | C8: =VLOOKUP(A8,'LHIND Academy Courses'!$A$1:$F$10,2,FALSE) -> AI: AI for Leaders | D8: Leadership | E8: edx / Microsoft | F8: Microsoft: AI Foundations for Business Leaders | G8: How leaders can use AI in business, responsible AI, governance, and human-in-the-loop decision models. | H8: Self-paced online (~2–3 hours) | I8: Free, paid certificate | J8: https://www.edx.org/learn/computer-science/microsoft-learning-path-introduction-to-ai-for-business-users | K8: Sharepoint gepflegt
A9: AI-08 | B9: AI-08-02 | C9: =VLOOKUP(A9,'LHIND Academy Courses'!$A$1:$F$10,2,FALSE) -> AI: AI for Leaders | D9: Leadership | E9: Coursera / IBM | F9: Introduction to GenAI for Executives | G9: Generative AI use cases, enterprise adoption, workforce transformation, productivity enablement, AI operating models, GenAI strategy. | H9: self-paced online, 3h | I9: 36€ monthly membership | J9: GenAI für Führungskräfte & Business Leaders: Eine Einführung | Coursera | K9: Sharepoint gepflegt
A10: AI-08 | B10: AI-08-03 | C10: =VLOOKUP(A10,'LHIND Academy Courses'!$A$1:$F$10,2,FALSE) -> AI: AI for Leaders | D10: Leadership | E10: MIT | F10: Applied Agentic AI for Organizational Transformation | G10: Advanced Course, [Optional] Agentic AI, autonomous AI agents, AI-enabled workflows, enterprise transformation, AI operating models, governance, organizational redesign, future-of-work leadership. | H10: 8 weeks, online | I10: US$2,720 | J10: Applied Agentic AI for Organizational Transformation | MIT Professional Education | K10: zu hohe Kosten für Kurs?
A11: AI-08 | B11: AI-08-04 | C11: =VLOOKUP(A11,'LHIND Academy Courses'!$A$1:$F$10,2,FALSE) -> AI: AI for Leaders | D11: Leadership | E11: Coursera | F11: AI Powered Decision Making | G11: [Optional] Advanced course on AI-driven decision models, predictive analytics, automation, and intelligent decision frameworks. | H11: ~34h | I11: 36€ monthly membership | J11: AI-Powered Decision Intelligence | Coursera | K11: Sharepoint gepflegt
A12: AI-09 | B12: AI-09-01 | C12: =VLOOKUP(A12,'LHIND Academy Courses'!$A$1:$F$10,2,FALSE) -> AI Fundamentals / AI for Everyone | D12: All LHIND employees | E12: DeepLearning.AI / Coursera | F12: AI for Everyone | G12: Non-technical introduction to AI concepts, terminology, business use cases, realistic capabilities and limits of AI, and ethical considerations. | H12: Self-paced online (~7 hours) | I12: 52€, paid certificate | J12: https://www.coursera.org/learn/ai-for-everyone | K12: Sharepoint gepflegt
A13: AI-09 | B13: AI-09-02 | C13: =VLOOKUP(A13,'LHIND Academy Courses'!$A$1:$F$10,2,FALSE) -> AI Fundamentals / AI for Everyone | D13: All LHIND employees | E13: Microsoft Learn | F13: Microsoft AI Learning Hub | G13: AI fundamentals, responsible AI, role-based learning paths, EU AI Act–aligned AI literacy resources. | H13: Modular, self-paced | I13: Free | J13: https://learn.microsoft.com/en-us/ai/ | K13: rausnehmen, bereits abgedeckt in AI-06-01
A14: AI-09 | B14: AI-09-03 | C14: =VLOOKUP(A14,'LHIND Academy Courses'!$A$1:$F$10,2,FALSE) -> AI Fundamentals / AI for Everyone | D14: All LHIND employees | E14: DeepLearning.AI / Coursera | F14: Generative KI für alle | G14: [Optional] Introduction to Generative AI and Large Language Models (LLMs), typical business applications, prompt engineering, and organizational adoption of GenAI.. | H14: Self-paced online (~6 hours) | I14: 52€, paid certificate | J14: https://www.coursera.org/learn/generative-ai-for-everyone?utm_source=chatgpt.com | K14: Sharepoint gepflegt
A15: AI-05 | B15: AI-05-01 | C15: AI: AI for Project Managers and Product Owners | D15: Project Management & Agility | E15: PMI | F15: Generative AI Overview for PMs | G15: Introductory course on AI and generative AI for project managers, covering core concepts, key terminology, GenAI use cases, a ChatGPT lab, and an AI tool library to improve project work. | H15: 3h | I15: Free | J15: PMI | K15: Sharepoint gepflegt
A16: AI-05 | B16: AI-05-02 | C16: AI: AI for Project Managers and Product Owners | D16: Project Management & Agility | E16: PMI | F16: Talking to AI: Prompt Engineering for Project Managers | G16: Practical introduction to prompt engineering for LLMs, teaching prompt formulas, refinement techniques, and many PM‑specific examples to get accurate, valuable outputs from tools like ChatGPT and PMI Infinity. | H16: 1h | I16: Free | J16: PMI | K16: Sharepoint gepflegt
A17: AI-05 | B17: AI-05-03 | C17: AI: AI for Project Managers and Product Owners | D17: Project Management & Agility | E17: LinkedIN | F17: Project Leadership in the Age of AI | G17: Course on combining AI capabilities with human leadership skills, showing how to use AI for analysis, forecasting, and communication while keeping ethics, empathy, and human‑centered project leadership in focus. | H17: 1h | I17: Subscription or free trial | J17: LinkedIN | K17: Sharepoint gepflegt
A18: AI-05 | B18: AI-05-04 | C18: AI: AI for Project Managers and Product Owners | D18: Project Management & Agility | E18: Coursera | F18: AI for Project Managers and Scrum Masters | G18: Short specialization that explains generative AI and prompt engineering basics, then applies them to planning, execution, and communication tasks in classic and agile project management contexts. | H18: 2h | I18: Free | J18: Coursera | K18: Sharepoint gepflegt
A19: AI-01 | B19: AI-01-01 | C19: AI: Foundation - Personal AI Productivity | D19: Technology Consulting | E19: Linkedin | F19: Integrating AI into the Product Architecture | G19: Learn to apply robust testing methodologies to ensure model performance, robustness, and fairness. Build scalable and maintainable AI integration patterns tailored to product requirements. Implement comprehensive monitoring and observability for AI models in production. Incorporate principles of explainable AI, uncertainty handling, and ethical AI practices into the user experience. | H19: 2.5 | I19: Free | J19: https://www.linkedin.com/learning/integrating-ai-into-the-product-architecture/course-introduction-and-prerequisites?u=2197772 | K19: Sharepoint gepflegt
A20: AI-01 | B20: AI-01-02 | C20: AI: Foundation - Personal AI Productivity | D20: Technology Consulting | E20: Linkedin | F20: Architectures for AI | G20: Understand the unique characteristics and design constraints for different types of AI architectures. Define the key architecture elements of AI across batch, real-time, cloud, and hybrid. Create an architecture for a given use case by analyzing requirements and choosing the right patterns and technologies. Scale the architecture to increase concurrency, response times, and throughput. | H20: 1.4 | I20: Free | J20: https://www.linkedin.com/learning/advanced-data-processing-batch-real-time-and-cloud-architectures-for-ai/architectures-for-ai?u=2197772 | K20: Sharepoint gepflegt
A21: AI-01 | B21: AI-01-03 | C21: AI: Foundation - Personal AI Productivity | D21: Technology Consulting | E21: Microsoft Learn | F21: Get started with AI applications and agents on Azure | G21: Generative AI and agents Text analysis Speech Computer vision Information extraction | H21: 5 | I21: Free | J21: https://learn.microsoft.com/en-us/training/paths/get-started-ai-apps-agents/ | K21: Sharepoint gepflegt
A22: AI-01 | B22: AI-01-04 | C22: AI: Foundation - Personal AI Productivity | D22: Technology Consulting | E22: Coursera | F22: Generative AI for Software Development Fähigkeitszertifikat | G22: Learn practical prompt engineering and pair programming techniques with LLMs to write, test, and improve your code. | H22: 20 | I22: Free | J22: https://www.coursera.org/professional-certificates/generative-ai-for-software-development | K22: Sharepoint gepflegt
A23: AI-04 | B23: AI-04.01 | C23: AI: Requirement Engineering with AI | D23: Business & Strategy Consulting | E23: Coursera | F23: How to Build an Enterprise AI Strategy | G23: Design an AI-powered business transformation strategy that drives innovation, operational efficiency, and sustainable competitive advantage. Build organizational capabilities and culture to support AI adoption strategy for enterprises. Develop AI business strategy roadmaps that balance quick wins with long-term business value. Optimize AI in the enterprise for measurable business impact, governance, and responsible deployment. | H23: 6 | I23: Free | J23: https://www.coursera.org/learn/how-to-build-an-enterprise-ai-strategy | K23: Sharepoint gepflegt
A24: AI-04 | B24: AI-04.02 | C24: AI: Requirement Engineering with AI | D24: Business & Strategy Consulting | E24: Linkedin | F24: AI for Managers | G24: In this learning path, managers at all levels of the organization will learn practical ways to enhance their effectiveness with generative AI—from making team and one-on-one meetings more effective to giving feedback that gets results. You'll also learn how to have meaningful career conversations with employees in an AI context, build a collaborative team culture with generative AI, and use AI responsibly. | H24: 5 | I24: Free | J24: https://www.linkedin.com/learning/paths/ai-for-managers-by-microsoft-and-linkedin?u=2197772 | K24: Sharepoint gepflegt
A25: AI-04 | B25: AI-04.03 | C25: AI: Requirement Engineering with AI | D25: Business & Strategy Consulting | E25: Coursera | F25: Specialization in “AI Leadership & Strategic Implementation” | G25: Use Generative AI to drive executive decisions, enterprise strategy, and sustainable transformation. | H25: 128 | I25: Free | J25: https://www.coursera.org/specializations/ai-leadership-and-strategic-implementation | K25: Sharepoint gepflegt
A26: AI-04 | B26: AI-04.04 | C26: AI: Requirement Engineering with AI | D26: Business & Strategy Consulting | E26: Coursera | F26: AI Strategy for Business Leaders | H26: 10 | I26: Free | J26: https://www.coursera.org/learn/packt-ai-strategy-for-business-leaders-with-chatgpt-ml-dl-uel66 | K26: Sharepoint gepflegt
A27: AI-03 | B27: AI-03-01 | C27: Engineering - AI Systems and Architecture | D27: Technology Consulting | E27: Coursera | F27: Artificial Intelligence on Microsoft Azure | G27: How to Identify Guiding Principles for Responsible AI | H27: 4 | I27: Free | J27: https://www.coursera.org/learn/artificial-intelligence-microsoft-azure | K27: Sharepoint gepflegt
A28: AI-03 | B28: AI-03-02 | C28: Engineering - AI Systems and Architecture | D28: Technology Consulting | E28: Coursera | F28: Specialization: “Generative AI for IT Systems Analysts and Architects” | G28: Build your skills using GenAI to analyze requirements, model processes, & deliver IT solutions fast. | H28: 24 | I28: Free | J28: https://www.coursera.org/specializations/generative-ai-it-systems-analysts-and-architects | K28: Sharepoint gepflegt
A29: AI-03 | B29: AI-03-03 | C29: Engineering - AI Systems and Architecture | D29: Technology Consulting | E29: Coursera | F29: Generative AI Architecture and Application Development | G29: Understand the core concepts of generative AI and large language models (LLMs). Design scalable architectures for AI-driven application development. Develop practical projects using AI frameworks and platforms. Apply ethical, compliant, and responsible AI practices in real-world deployments. | H29: 10 | I29: Free | J29: https://www.coursera.org/learn/generative-ai-architecture-and-application-development | K29: Sharepoint gepflegt
A30: AI-03 | B30: AI-03-04 | C30: Engineering - AI Systems and Architecture | D30: Technology Consulting | E30: Coursera | F30: Architecture of AI Solutions - Scalable GenAI Systems | G30: Master the fundamental principles of scalable generative AI systems and architectures. Gain hands-on experience with the LGPL architecture, including gates, pipes, and loops. Learn how to build resilient and fault-tolerant GenAI applications using modern infrastructure tools. Understand advanced topics such as explainable AI (XAI), MLOps, and emerging trends in GenAI. | H30: 6 | I30: Free | J30: https://www.coursera.org/learn/packt-architecting-ai-solutions-scalable-genai-systems-btzcm | K30: Sharepoint gepflegt
A31: AI-03 | B31: AI-03-05 | C31: Engineering - AI Systems and Architecture | D31: Technology Consulting | E31: Coursera | F31: Generative AI and Large Language Models: Architecture and Data Preparation | H31: 6 | I31: Free | J31: https://www.coursera.org/learn/generative-ai-llm-architecture-data-preparation | K31: Sharepoint gepflegt
A32: AI-02 | B32: AI-02-01 | C32: AI: Agentic Software Engineering | D32: Technology Consulting | E32: Coursera | F32: Spezialisierung „Building AI Agents and Agentic Workflows“ | G32: Develop agentic AI applications that integrate tools, support reasoning, and improve performance through reflection | H32: 40 | I32: Free | J32: https://www.coursera.org/specializations/building-ai-agents-and-agentic-workflows | K32: Sharepoint gepflegt
A33: AI-02 | B33: AI-02-02 | C33: AI: Agentic Software Engineering | D33: Technology Consulting | E33: Coursera | F33: Agentic AI Engineering | G33: Explain how agentic AI systems operate, including models, prompts, tools, and orchestration patterns used in modern AI applications. | H33: 72 | I33: Free | J33: https://www.coursera.org/specializations/agentic-ai-engineering | K33: Sharepoint gepflegt
A34: AI-02 | B34: AI-02-03 | C34: AI: Agentic Software Engineering | D34: Technology Consulting | E34: Linkedin | F34: Building Agentic AI Systems for Developers | H34: 15 | I34: Free | J34: https://www.linkedin.com/learning/paths/building-agentic-ai-systems-for-developers?u=2197772 | K34: Sharepoint gepflegt
A35: AI-02 | B35: AI-02-04 | C35: AI: Agentic Software Engineering | D35: Technology Consulting | E35: Linkedin | F35: Agentic AI Fundamentals: Architectures, Frameworks, and Applications | H35: 1.15 | I35: Free | J35: https://www.linkedin.com/learning/agentic-ai-fundamentals-architectures-frameworks-and-applications/what-is-agentic-ai?autoSkip=true&resume=false&u=2197772 | K35: Sharepoint gepflegt

Sheet ignore
A1: LHIND Academy Training | B1: Module ID | C1: Titel | D1: Primary Role | E1: Provider | F1: Module/Course Name | G1: Module Course Content Summary | H1: Format | I1: Cost | J1: URL
A2: AI-06 | B2: AI-06-01 | C2: =VLOOKUP(A2,'LHIND Academy Courses'!$A$1:$F$10,2,FALSE) -> AI: Introduction to Concepts and Tools for Personal Productivity | D2: All LHIND employees | E2: Microsoft Learn | F2: AI for Business Users (Use AI for everyday tasks) | G2: Hands-on generative AI for daily productivity: prompting, writing, summarizing, ideation, responsible AI usage. | H2: Self-paced online (~1 hour) | I2: Free | J2: https://learn.microsoft.com/de-de/training/modules/use-ai-everyday-tasks/
A3: AI-06 | B3: AI-06-02 | C3: =VLOOKUP(A3,'[1]LHIND Academy Trainings'!$A$1:$F$10,2,FALSE) -> AI: Introduction to Concepts and Tools for Personal Productivity | D3: All LHIND employees | E3: Google / Coursera | F3: Google AI Fundamentals | G3: Using AI as a professional work assistant, prompt frameworks, evaluating output quality, bias awareness. | H3: Self-paced online (~3 hours) | I3: Coursera subscription | J3: https://www.coursera.org/learn/google-ai-fundamentals
A4: AI-06 | B4: AI-06-03 | C4: =VLOOKUP(A4,'[1]LHIND Academy Trainings'!$A$1:$F$10,2,FALSE) -> AI: Introduction to Concepts and Tools for Personal Productivity | D4: All LHIND employees | E4: Coursera | F4: Real-World AI for Everyone | G4: [Optional] Claude focused. Fokus auf praktische Nutzung von AI Assistants wie Claude im Berufsalltag: Kommunikation, Dokumente, Analysen, Workflows und Zusammenarbeit mit AI. | H4: Ca. 6-10 h | I4: Free | J4: Real-World AI for Everyone | Coursera
A5: AI-06 | B5: AI-06-04 | C5: =VLOOKUP(A5,'[1]LHIND Academy Trainings'!$A$1:$F$10,2,FALSE) -> AI: Introduction to Concepts and Tools for Personal Productivity | D5: All LHIND employees | E5: LHIND | F5: Introduction to LHIND tools and best practices | G5: Introduction to LHIND available tools, LHIND/LHG guidelines and best practices | H5: Instructor-led, ~2-3h | J5: TBD | K5: *- smart assistsant - copilot - Claude Code - | L5: 1 Stunde Überblick 2 (1,5h) Hands on LHIND AI Skills | M5: 2-3Trainer suchen, Mark
A6: AI-07 | B6: AI-07-01 | C6: =VLOOKUP(A6,'[1]LHIND Academy Trainings'!$A$1:$F$10,2,FALSE) -> AI: Introduction to Data-driven Decision Making | D6: Leadership | E6: Coursera | F6: AI‑Augmented Decision‑Making for Business Leaders | G6: AI-supported decision making, forecasting, bias, uncertainty, ethics, and leadership accountability. | H6: ~ 4h | I6: Free | J6: https://www.coursera.org/learn/ai-augmented-decision-making-for-business-leaders
A7: AI-07 | B7: AI-07-02 | C7: =VLOOKUP(A7,'[1]LHIND Academy Trainings'!$A$1:$F$10,2,FALSE) -> AI: Introduction to Data-driven Decision Making | D7: Leadership | E7: Coursera | F7: AI Powered Decision Making | G7: [Optional] Fortgeschrittener Kurs zu AI-gestützten Entscheidungsmodellen, Predictive Analytics, Automatisierung und intelligenten Decision Frameworks. | H7: ~34h | I7: Free | J7: AI-Powered Decision Intelligence | Coursera
A8: AI-08 | B8: AI-08-01 | C8: =VLOOKUP(A8,'[1]LHIND Academy Trainings'!$A$1:$F$10,2,FALSE) -> AI: AI for Leaders | D8: Leadership | E8: edx / Microsoft | F8: Microsoft: AI Foundations for Business Leaders | G8: How leaders can use AI in business, responsible AI, governance, and human-in-the-loop decision models. | H8: Self-paced online (~2–3 hours) | I8: Free, paid certificate | J8: https://www.edx.org/learn/computer-science/microsoft-learning-path-introduction-to-ai-for-business-users
A9: AI-08 | B9: AI-08-02 | C9: =VLOOKUP(A9,'[1]LHIND Academy Trainings'!$A$1:$F$10,2,FALSE) -> AI: AI for Leaders | D9: Leadership | E9: Coursera / IBM | F9: Introduction to GenAI for Executives | G9: Generative AI use cases, enterprise adoption, workforce transformation, productivity enablement, AI operating models, GenAI strategy. | H9: self-paced online, 3h | I9: 36€ monthly membership | J9: GenAI für Führungskräfte & Business Leaders: Eine Einführung | Coursera
A10: AI-08 | B10: AI-08-03 | C10: =VLOOKUP(A10,'[1]LHIND Academy Trainings'!$A$1:$F$10,2,FALSE) -> AI: AI for Leaders | D10: Leadership | E10: MIT | F10: Applied Agentic AI for Organizational Transformation | G10: Advanced Course, [Optional] Agentic AI, autonomous AI agents, AI-enabled workflows, enterprise transformation, AI operating models, governance, organizational redesign, future-of-work leadership. | H10: 8 weeks, online | I10: US$2,720 | J10: Applied Agentic AI for Organizational Transformation | MIT Professional Education
A11: AI-08 | B11: AI-08-04 | C11: =VLOOKUP(A11,'[1]LHIND Academy Trainings'!$A$1:$F$10,2,FALSE) -> AI: AI for Leaders | D11: Leadership | E11: Coursera | F11: AI Powered Decision Making | G11: [Optional] Advanced course on AI-driven decision models, predictive analytics, automation, and intelligent decision frameworks. | H11: ~34h | I11: 36€ monthly membership | J11: AI-Powered Decision Intelligence | Coursera
A12: AI-09 | B12: AI-09-01 | C12: =VLOOKUP(A12,'[1]LHIND Academy Trainings'!$A$1:$F$10,2,FALSE) -> AI Fundamentals / AI for Everyone | D12: All LHIND employees | E12: DeepLearning.AI / Coursera | F12: AI for Everyone | G12: Non-technical introduction to AI concepts, terminology, business use cases, realistic capabilities and limits of AI, and ethical considerations. | H12: Self-paced online (~7 hours) | I12: 52€, paid certificate | J12: https://www.coursera.org/learn/ai-for-everyone
A13: AI-09 | B13: AI-09-02 | C13: =VLOOKUP(A13,'[1]LHIND Academy Trainings'!$A$1:$F$10,2,FALSE) -> AI Fundamentals / AI for Everyone | D13: All LHIND employees | E13: Microsoft Learn | F13: Microsoft AI Learning Hub | G13: AI fundamentals, responsible AI, role-based learning paths, EU AI Act–aligned AI literacy resources. | H13: Modular, self-paced | I13: Free | J13: https://learn.microsoft.com/en-us/ai/
A14: AI-09 | B14: AI-09-03 | C14: =VLOOKUP(A14,'[1]LHIND Academy Trainings'!$A$1:$F$10,2,FALSE) -> AI Fundamentals / AI for Everyone | D14: All LHIND employees | E14: DeepLearning.AI / Coursera | F14: Generative KI für alle | G14: [Optional] Introduction to Generative AI and Large Language Models (LLMs), typical business applications, prompt engineering, and organizational adoption of GenAI.. | H14: Self-paced online (~6 hours) | I14: 52€, paid certificate | J14: https://www.coursera.org/learn/generative-ai-for-everyone?utm_source=chatgpt.com
A15: AI-05 | B15: AI-05-01 | C15: AI: AI for Project Managers and Product Owners | D15: Project Management & Agility | E15: PMI | F15: Generative AI Overview for PMs | G15: Introductory course on AI and generative AI for project managers, covering core concepts, key terminology, GenAI use cases, a ChatGPT lab, and an AI tool library to improve project work. | H15: 3h | I15: Free | J15: PMI
A16: AI-05 | B16: AI-05-02 | C16: AI: AI for Project Managers and Product Owners | D16: Project Management & Agility | E16: PMI | F16: Talking to AI: Prompt Engineering for Project Managers | G16: Practical introduction to prompt engineering for LLMs, teaching prompt formulas, refinement techniques, and many PM‑specific examples to get accurate, valuable outputs from tools like ChatGPT and PMI Infinity. | H16: 1h | I16: Free | J16: PMI
A17: AI-05 | B17: AI-05-03 | C17: AI: AI for Project Managers and Product Owners | D17: Project Management & Agility | E17: LinkedIN | F17: Project Leadership in the Age of AI | G17: Course on combining AI capabilities with human leadership skills, showing how to use AI for analysis, forecasting, and communication while keeping ethics, empathy, and human‑centered project leadership in focus. | H17: 1h | I17: Subscription or free trial | J17: LinkedIN
A18: AI-05 | B18: AI-05-04 | C18: AI: AI for Project Managers and Product Owners | D18: Project Management & Agility | E18: Coursera | F18: AI for Project Managers and Scrum Masters | G18: Short specialization that explains generative AI and prompt engineering basics, then applies them to planning, execution, and communication tasks in classic and agile project management contexts. | H18: 2h | I18: Free | J18: Coursera
A19: AI-01 | B19: AI-01-01 | C19: AI: Foundation - Personal AI Productivity | D19: Technology Consulting | E19: Linkedin | F19: Integrating AI into the Product Architecture | G19: Learn to apply robust testing methodologies to ensure model performance, robustness, and fairness. Build scalable and maintainable AI integration patterns tailored to product requirements. Implement comprehensive monitoring and observability for AI models in production. Incorporate principles of explainable AI, uncertainty handling, and ethical AI practices into the user experience. | H19: 2.5 | I19: Free | J19: https://www.linkedin.com/learning/integrating-ai-into-the-product-architecture/course-introduction-and-prerequisites?u=2197772
A20: AI-01 | B20: AI-01-02 | C20: AI: Foundation - Personal AI Productivity | D20: Technology Consulting | E20: Linkedin | F20: Architectures for AI | G20: Understand the unique characteristics and design constraints for different types of AI architectures. Define the key architecture elements of AI across batch, real-time, cloud, and hybrid. Create an architecture for a given use case by analyzing requirements and choosing the right patterns and technologies. Scale the architecture to increase concurrency, response times, and throughput. | H20: 1.4 | I20: Free | J20: https://www.linkedin.com/learning/advanced-data-processing-batch-real-time-and-cloud-architectures-for-ai/architectures-for-ai?u=2197772
A21: AI-01 | B21: AI-01-03 | C21: AI: Foundation - Personal AI Productivity | D21: Technology Consulting | E21: Microsoft Learn | F21: Get started with AI applications and agents on Azure | G21: Generative AI and agents Text analysis Speech Computer vision Information extraction | H21: 5 | I21: Free | J21: https://learn.microsoft.com/en-us/training/paths/get-started-ai-apps-agents/
A22: AI-01 | B22: AI-01-04 | C22: AI: Foundation - Personal AI Productivity | D22: Technology Consulting | E22: Coursera | F22: Generative AI for Software Development Fähigkeitszertifikat | G22: Learn practical prompt engineering and pair programming techniques with LLMs to write, test, and improve your code. | H22: 20 | I22: Free | J22: https://www.coursera.org/professional-certificates/generative-ai-for-software-development
A23: AI-04 | B23: AI-04.01 | C23: AI: Requirement Engineering with AI | D23: Business & Strategy Consulting | E23: Coursera | F23: How to Build an Enterprise AI Strategy | G23: Design an AI-powered business transformation strategy that drives innovation, operational efficiency, and sustainable competitive advantage. Build organizational capabilities and culture to support AI adoption strategy for enterprises. Develop AI business strategy roadmaps that balance quick wins with long-term business value. Optimize AI in the enterprise for measurable business impact, governance, and responsible deployment. | H23: 6 | I23: Free | J23: https://www.coursera.org/learn/how-to-build-an-enterprise-ai-strategy
A24: AI-04 | B24: AI-04.02 | C24: AI: Requirement Engineering with AI | D24: Business & Strategy Consulting | E24: Linkedin | F24: AI for Managers | G24: In this learning path, managers at all levels of the organization will learn practical ways to enhance their effectiveness with generative AI—from making team and one-on-one meetings more effective to giving feedback that gets results. You'll also learn how to have meaningful career conversations with employees in an AI context, build a collaborative team culture with generative AI, and use AI responsibly. | H24: 5 | I24: Free | J24: https://www.linkedin.com/learning/paths/ai-for-managers-by-microsoft-and-linkedin?u=2197772
A25: AI-04 | B25: AI-04.03 | C25: AI: Requirement Engineering with AI | D25: Business & Strategy Consulting | E25: Coursera | F25: Specialization in “AI Leadership & Strategic Implementation” | G25: Use Generative AI to drive executive decisions, enterprise strategy, and sustainable transformation. | H25: 128 | I25: Free | J25: https://www.coursera.org/specializations/ai-leadership-and-strategic-implementation
A26: AI-04 | B26: AI-04.04 | C26: AI: Requirement Engineering with AI | D26: Business & Strategy Consulting | E26: Coursera | F26: AI Strategy for Business Leaders | H26: 10 | I26: Free | J26: https://www.coursera.org/learn/packt-ai-strategy-for-business-leaders-with-chatgpt-ml-dl-uel66
A27: AI-03 | B27: AI-03-01 | C27: Engineering - AI Systems and Architecture | D27: Technology Consulting | E27: Coursera | F27: Artificial Intelligence on Microsoft Azure | G27: How to Identify Guiding Principles for Responsible AI | H27: 4 | I27: Free | J27: https://www.coursera.org/learn/artificial-intelligence-microsoft-azure
A28: AI-03 | B28: AI-03-02 | C28: Engineering - AI Systems and Architecture | D28: Technology Consulting | E28: Coursera | F28: Specialization: “Generative AI for IT Systems Analysts and Architects” | G28: Build your skills using GenAI to analyze requirements, model processes, & deliver IT solutions fast. | H28: 24 | I28: Free | J28: https://www.coursera.org/specializations/generative-ai-it-systems-analysts-and-architects
A29: AI-03 | B29: AI-03-03 | C29: Engineering - AI Systems and Architecture | D29: Technology Consulting | E29: Coursera | F29: Generative AI Architecture and Application Development | G29: Understand the core concepts of generative AI and large language models (LLMs). Design scalable architectures for AI-driven application development. Develop practical projects using AI frameworks and platforms. Apply ethical, compliant, and responsible AI practices in real-world deployments. | H29: 10 | I29: Free | J29: https://www.coursera.org/learn/generative-ai-architecture-and-application-development
A30: AI-03 | B30: AI-03-04 | C30: Engineering - AI Systems and Architecture | D30: Technology Consulting | E30: Coursera | F30: Architecture of AI Solutions - Scalable GenAI Systems | G30: Master the fundamental principles of scalable generative AI systems and architectures. Gain hands-on experience with the LGPL architecture, including gates, pipes, and loops. Learn how to build resilient and fault-tolerant GenAI applications using modern infrastructure tools. Understand advanced topics such as explainable AI (XAI), MLOps, and emerging trends in GenAI. | H30: 6 | I30: Free | J30: https://www.coursera.org/learn/packt-architecting-ai-solutions-scalable-genai-systems-btzcm
A31: AI-03 | B31: AI-03-05 | C31: Engineering - AI Systems and Architecture | D31: Technology Consulting | E31: Coursera | F31: Generative AI and Large Language Models: Architecture and Data Preparation | H31: 6 | I31: Free | J31: https://www.coursera.org/learn/generative-ai-llm-architecture-data-preparation
A32: AI-02 | B32: AI-02-01 | C32: AI: Agentic Software Engineering | D32: Technology Consulting | E32: Coursera | F32: Spezialisierung „Building AI Agents and Agentic Workflows“ | G32: Develop agentic AI applications that integrate tools, support reasoning, and improve performance through reflection | H32: 40 | I32: Free | J32: https://www.coursera.org/specializations/building-ai-agents-and-agentic-workflows
A33: AI-02 | B33: AI-02-02 | C33: AI: Agentic Software Engineering | D33: Technology Consulting | E33: Coursera | F33: Agentic AI Engineering | G33: Explain how agentic AI systems operate, including models, prompts, tools, and orchestration patterns used in modern AI applications. | H33: 72 | I33: Free | J33: https://www.coursera.org/specializations/agentic-ai-engineering
A34: AI-02 | B34: AI-02-03 | C34: AI: Agentic Software Engineering | D34: Technology Consulting | E34: Linkedin | F34: Building Agentic AI Systems for Developers | H34: 15 | I34: Free | J34: https://www.linkedin.com/learning/paths/building-agentic-ai-systems-for-developers?u=2197772
A35: AI-02 | B35: AI-02-04 | C35: AI: Agentic Software Engineering | D35: Technology Consulting | E35: Linkedin | F35: Agentic AI Fundamentals: Architectures, Frameworks, and Applications | H35: 1.15 | I35: Free | J35: https://www.linkedin.com/learning/agentic-ai-fundamentals-architectures-frameworks-and-applications/what-is-agentic-ai?autoSkip=true&resume=false&u=2197772
